{"yield_curves": {"kr": {"curve": [{"tenor": "1Y", "yield": 3.238}, {"tenor": "2Y", "yield": 3.605}, {"tenor": "3Y", "yield": 3.744}, {"tenor": "5Y", "yield": 3.917}, {"tenor": "10Y", "yield": 4.118}, {"tenor": "20Y", "yield": 4.245}, {"tenor": "30Y", "yield": 4.181}], "curve_shape": "normal"}, "us": {"curve": [{"tenor": "1M", "yield": 3.71}, {"tenor": "3M", "yield": 3.87}, {"tenor": "6M", "yield": 4.0}, {"tenor": "1Y", "yield": 3.97}, {"tenor": "2Y", "yield": 4.1}, {"tenor": "3Y", "yield": 4.1}, {"tenor": "5Y", "yield": 4.14}, {"tenor": "7Y", "yield": 4.24}, {"tenor": "10Y", "yield": 4.38}, {"tenor": "20Y", "yield": 4.86}, {"tenor": "30Y", "yield": 4.86}], "curve_shape": "normal", "spread_2y_10y": 0.28, "spread_3m_10y": 0.51}}, "inversion_alerts": [], "has_alert": false, "updated_at": "2026-07-01T08:37:27+09:00", "credit_spreads": {"us_ig_oas": 0.95, "us_ig_risk": "LOW", "us_hy_oas": 2.8, "us_hy_risk": "LOW"}, "bond_regime": {"rate_environment": "rate_elevated", "curve_shape": "normal", "credit_cycle": "tightening", "recession_signal": false, "macro_override": false}}