{
  "updated_at": "2026-06-24T08:23:53+09:00",
  "mom_alert_threshold_pct": 10.0,
  "commodity_mom_alerts": [
    {
      "commodity_ticker": "CL=F",
      "vs_prior_month_avg_pct": -25.98,
      "last_close": 72.92
    },
    {
      "commodity_ticker": "GC=F",
      "vs_prior_month_avg_pct": -10.28,
      "last_close": 4117.8999
    }
  ],
  "high_correlation": [
    {
      "ticker": "EOG",
      "name": "EOG",
      "commodity": "CL=F",
      "correlation_60d": 0.6928,
      "regime": "동반 약세"
    },
    {
      "ticker": "NEM",
      "name": "NEM",
      "commodity": "LIT",
      "correlation_60d": 0.6647,
      "regime": "동반 약세"
    },
    {
      "ticker": "EXE",
      "name": "EXE",
      "commodity": "NG=F",
      "correlation_60d": 0.5049,
      "regime": "최악의 상황"
    },
    {
      "ticker": "EQT",
      "name": "EQT",
      "commodity": "NG=F",
      "correlation_60d": 0.4741,
      "regime": "최악의 상황"
    },
    {
      "ticker": "RRC",
      "name": "RRC",
      "commodity": "NG=F",
      "correlation_60d": 0.4688,
      "regime": "최악의 상황"
    }
  ],
  "by_ticker": {
    "003550": {
      "sector": "Technology",
      "commodity_tickers": [
        "LIT",
        "HG=F"
      ],
      "primary": {
        "commodity_ticker": "HG=F",
        "correlation_60d": null,
        "commodity_20d_pct": -3.41,
        "stock_20d_pct": -16.79,
        "spread_regime": "동반 약세",
        "safety_adjustment": -5,
        "pricing_power": 100.0,
        "raw_material_volatility_score": 68.4,
        "margin_safety_score": 32.65,
        "shock_analysis": {
          "windows": 0,
          "avg_stock_when_commodity_shock_pct": null
        },
        "vs_prior_month_avg_pct": -2.21
      }
    },
    "100840": {
      "sector": "Industrials",
      "commodity_tickers": [
        "HG=F",
        "CL=F"
      ],
      "primary": {
        "commodity_ticker": "CL=F",
        "correlation_60d": null,
        "commodity_20d_pct": -24.51,
        "stock_20d_pct": -33.26,
        "spread_regime": "동반 약세",
        "safety_adjustment": -5,
        "pricing_power": 78.7,
        "raw_material_volatility_score": 100.0,
        "margin_safety_score": 7.19,
        "shock_analysis": {
          "windows": 0,
          "avg_stock_when_commodity_shock_pct": null
        },
        "vs_prior_month_avg_pct": -25.98
      }
    },
    "114090": {
      "sector": "Consumer Cyclical",
      "commodity_tickers": [
        "CL=F",
        "ZC=F"
      ],
      "primary": {
        "commodity_ticker": "ZC=F",
        "correlation_60d": null,
        "commodity_20d_pct": -3.41,
        "stock_20d_pct": -6.91,
        "spread_regime": "동반 약세",
        "safety_adjustment": -5,
        "pricing_power": 81.5,
        "raw_material_volatility_score": 68.4,
        "margin_safety_score": 21.55,
        "shock_analysis": {
          "windows": 0,
          "avg_stock_when_commodity_shock_pct": null
        },
        "vs_prior_month_avg_pct": -2.21
      }
    },
    "035420": {
      "sector": "Communication Services",
      "commodity_tickers": [
        "HG=F",
        "NG=F"
      ],
      "primary": {
        "commodity_ticker": "NG=F",
        "correlation_60d": null,
        "commodity_20d_pct": 9.84,
        "stock_20d_pct": -0.25,
        "spread_regime": "비용 압박",
        "safety_adjustment": -20,
        "pricing_power": 72.8,
        "raw_material_volatility_score": 100.0,
        "margin_safety_score": 3.68,
        "shock_analysis": {
          "windows": 0,
          "avg_stock_when_commodity_shock_pct": null
        },
        "vs_prior_month_avg_pct": 8.72
      }
    },
    "000270": {
      "sector": "Consumer Cyclical",
      "commodity_tickers": [
        "CL=F",
        "ZC=F"
      ],
      "primary": {
        "commodity_ticker": "ZC=F",
        "correlation_60d": null,
        "commodity_20d_pct": -3.41,
        "stock_20d_pct": -16.63,
        "spread_regime": "동반 약세",
        "safety_adjustment": -5,
        "pricing_power": 51.1,
        "raw_material_volatility_score": 68.4,
        "margin_safety_score": 3.34,
        "shock_analysis": {
          "windows": 0,
          "avg_stock_when_commodity_shock_pct": null
        },
        "vs_prior_month_avg_pct": -2.21
      }
    },
    "028050": {
      "sector": "Industrials",
      "commodity_tickers": [
        "HG=F",
        "CL=F"
      ],
      "primary": {
        "commodity_ticker": "CL=F",
        "correlation_60d": null,
        "commodity_20d_pct": -24.51,
        "stock_20d_pct": -16.01,
        "spread_regime": "동반 약세",
        "safety_adjustment": -5,
        "pricing_power": 53.2,
        "raw_material_volatility_score": 100.0,
        "margin_safety_score": -8.11,
        "shock_analysis": {
          "windows": 0,
          "avg_stock_when_commodity_shock_pct": null
        },
        "vs_prior_month_avg_pct": -25.98
      }
    },
    "214450": {
      "sector": "Healthcare",
      "commodity_tickers": [
        "CL=F",
        "HG=F"
      ],
      "primary": {
        "commodity_ticker": "HG=F",
        "correlation_60d": null,
        "commodity_20d_pct": -3.41,
        "stock_20d_pct": -8.2,
        "spread_regime": "최악의 상황",
        "safety_adjustment": -50,
        "pricing_power": 92.8,
        "raw_material_volatility_score": 68.4,
        "margin_safety_score": 28.33,
        "shock_analysis": {
          "windows": 0,
          "avg_stock_when_commodity_shock_pct": null
        },
        "vs_prior_month_avg_pct": -2.21
      }
    },
    "017960": {
      "sector": "Basic Materials",
      "commodity_tickers": [
        "HG=F",
        "LIT"
      ],
      "primary": {
        "commodity_ticker": "LIT",
        "correlation_60d": null,
        "commodity_20d_pct": -8.03,
        "stock_20d_pct": -23.91,
        "spread_regime": "동반 약세",
        "safety_adjustment": -5,
        "pricing_power": 92.2,
        "raw_material_volatility_score": 87.6,
        "margin_safety_score": 20.26,
        "shock_analysis": {
          "windows": 0,
          "avg_stock_when_commodity_shock_pct": null
        },
        "vs_prior_month_avg_pct": -9.93
      }
    },
    "035900": {
      "sector": "Communication Services",
      "commodity_tickers": [
        "HG=F",
        "NG=F"
      ],
      "primary": {
        "commodity_ticker": "NG=F",
        "correlation_60d": null,
        "commodity_20d_pct": 9.84,
        "stock_20d_pct": -17.69,
        "spread_regime": "최악의 상황",
        "safety_adjustment": -50,
        "pricing_power": 78.1,
        "raw_material_volatility_score": 100.0,
        "margin_safety_score": 6.83,
        "shock_analysis": {
          "windows": 0,
          "avg_stock_when_commodity_shock_pct": null
        },
        "vs_prior_month_avg_pct": 8.72
      }
    },
    "009540": {
      "sector": "Industrials",
      "commodity_tickers": [
        "HG=F",
        "CL=F"
      ],
      "primary": {
        "commodity_ticker": "CL=F",
        "correlation_60d": null,
        "commodity_20d_pct": -24.51,
        "stock_20d_pct": -13.42,
        "spread_regime": "동반 약세",
        "safety_adjustment": -5,
        "pricing_power": 86.8,
        "raw_material_volatility_score": 100.0,
        "margin_safety_score": 12.05,
        "shock_analysis": {
          "windows": 0,
          "avg_stock_when_commodity_shock_pct": null
        },
        "vs_prior_month_avg_pct": -25.98
      }
    },
    "CTSH": {
      "sector": "Technology",
      "commodity_tickers": [
        "LIT",
        "HG=F"
      ],
      "primary": {
        "commodity_ticker": "HG=F",
        "correlation_60d": 0.0344,
        "commodity_20d_pct": -3.41,
        "stock_20d_pct": -22.37,
        "spread_regime": "동반 약세",
        "safety_adjustment": -5,
        "pricing_power": 61.5,
        "raw_material_volatility_score": 68.4,
        "margin_safety_score": 9.55,
        "shock_analysis": {
          "windows": 15,
          "avg_stock_when_commodity_shock_pct": -3.53
        },
        "vs_prior_month_avg_pct": -2.21
      }
    },
    "ACN": {
      "sector": "Technology",
      "commodity_tickers": [
        "LIT",
        "HG=F"
      ],
      "primary": {
        "commodity_ticker": "LIT",
        "correlation_60d": -0.0191,
        "commodity_20d_pct": -8.03,
        "stock_20d_pct": -29.14,
        "spread_regime": "동반 약세",
        "safety_adjustment": -5,
        "pricing_power": 65.0,
        "raw_material_volatility_score": 87.6,
        "margin_safety_score": 3.97,
        "shock_analysis": {
          "windows": 50,
          "avg_stock_when_commodity_shock_pct": -4.88
        },
        "vs_prior_month_avg_pct": -9.93
      }
    },
    "EXE": {
      "sector": "Energy",
      "commodity_tickers": [
        "CL=F",
        "NG=F"
      ],
      "primary": {
        "commodity_ticker": "NG=F",
        "correlation_60d": 0.5049,
        "commodity_20d_pct": 9.84,
        "stock_20d_pct": -9.4,
        "spread_regime": "최악의 상황",
        "safety_adjustment": -50,
        "pricing_power": 77.5,
        "raw_material_volatility_score": 100.0,
        "margin_safety_score": 6.5,
        "shock_analysis": {
          "windows": 37,
          "avg_stock_when_commodity_shock_pct": -1.98
        },
        "vs_prior_month_avg_pct": 8.72
      }
    },
    "VSNT": {
      "sector": "Communication Services",
      "commodity_tickers": [
        "HG=F",
        "NG=F"
      ],
      "primary": {
        "commodity_ticker": "HG=F",
        "correlation_60d": 0.199,
        "commodity_20d_pct": -3.41,
        "stock_20d_pct": -11.23,
        "spread_regime": "동반 약세",
        "safety_adjustment": -5,
        "pricing_power": 77.5,
        "raw_material_volatility_score": 68.4,
        "margin_safety_score": 19.15,
        "shock_analysis": {
          "windows": 15,
          "avg_stock_when_commodity_shock_pct": 11.79
        },
        "vs_prior_month_avg_pct": -2.21
      }
    },
    "EQT": {
      "sector": "Energy",
      "commodity_tickers": [
        "CL=F",
        "NG=F"
      ],
      "primary": {
        "commodity_ticker": "NG=F",
        "correlation_60d": 0.4741,
        "commodity_20d_pct": 9.84,
        "stock_20d_pct": -10.81,
        "spread_regime": "최악의 상황",
        "safety_adjustment": -50,
        "pricing_power": 77.5,
        "raw_material_volatility_score": 100.0,
        "margin_safety_score": 6.5,
        "shock_analysis": {
          "windows": 37,
          "avg_stock_when_commodity_shock_pct": -3.17
        },
        "vs_prior_month_avg_pct": 8.72
      }
    },
    "EOG": {
      "sector": "Energy",
      "commodity_tickers": [
        "CL=F",
        "NG=F"
      ],
      "primary": {
        "commodity_ticker": "CL=F",
        "correlation_60d": 0.6928,
        "commodity_20d_pct": -24.51,
        "stock_20d_pct": -4.48,
        "spread_regime": "동반 약세",
        "safety_adjustment": -5,
        "pricing_power": 77.5,
        "raw_material_volatility_score": 100.0,
        "margin_safety_score": 6.5,
        "shock_analysis": {
          "windows": 29,
          "avg_stock_when_commodity_shock_pct": 6.34
        },
        "vs_prior_month_avg_pct": -25.98
      }
    },
    "LEN": {
      "sector": "Consumer Cyclical",
      "commodity_tickers": [
        "CL=F",
        "ZC=F"
      ],
      "primary": {
        "commodity_ticker": "CL=F",
        "correlation_60d": -0.418,
        "commodity_20d_pct": -24.51,
        "stock_20d_pct": -1.7,
        "spread_regime": "중립",
        "safety_adjustment": 0,
        "pricing_power": 35.8,
        "raw_material_volatility_score": 100.0,
        "margin_safety_score": -18.55,
        "shock_analysis": {
          "windows": 29,
          "avg_stock_when_commodity_shock_pct": -7.35
        },
        "vs_prior_month_avg_pct": -25.98
      }
    },
    "INGR": {
      "sector": "Consumer Defensive",
      "commodity_tickers": [
        "ZC=F",
        "CL=F"
      ],
      "primary": {
        "commodity_ticker": "CL=F",
        "correlation_60d": -0.0846,
        "commodity_20d_pct": -24.51,
        "stock_20d_pct": -4.33,
        "spread_regime": "동반 약세",
        "safety_adjustment": -5,
        "pricing_power": 52.2,
        "raw_material_volatility_score": 100.0,
        "margin_safety_score": -8.65,
        "shock_analysis": {
          "windows": 29,
          "avg_stock_when_commodity_shock_pct": -2.71
        },
        "vs_prior_month_avg_pct": -25.98
      }
    },
    "HLNE": {
      "sector": "Financial Services",
      "commodity_tickers": [
        "GC=F",
        "CL=F"
      ],
      "primary": {
        "commodity_ticker": "CL=F",
        "correlation_60d": -0.243,
        "commodity_20d_pct": -24.51,
        "stock_20d_pct": -15.64,
        "spread_regime": "동반 약세",
        "safety_adjustment": -5,
        "pricing_power": 77.5,
        "raw_material_volatility_score": 100.0,
        "margin_safety_score": 6.5,
        "shock_analysis": {
          "windows": 29,
          "avg_stock_when_commodity_shock_pct": -9.22
        },
        "vs_prior_month_avg_pct": -25.98
      }
    },
    "KHC": {
      "sector": "Consumer Defensive",
      "commodity_tickers": [
        "ZC=F",
        "CL=F"
      ],
      "primary": {
        "commodity_ticker": "CL=F",
        "correlation_60d": 0.0895,
        "commodity_20d_pct": -24.51,
        "stock_20d_pct": -3.84,
        "spread_regime": "동반 약세",
        "safety_adjustment": -5,
        "pricing_power": 74.2,
        "raw_material_volatility_score": 100.0,
        "margin_safety_score": 4.55,
        "shock_analysis": {
          "windows": 29,
          "avg_stock_when_commodity_shock_pct": 1.98
        },
        "vs_prior_month_avg_pct": -25.98
      }
    },
    "CAG": {
      "sector": "Consumer Defensive",
      "commodity_tickers": [
        "ZC=F",
        "CL=F"
      ],
      "primary": {
        "commodity_ticker": "ZC=F",
        "correlation_60d": 0.2396,
        "commodity_20d_pct": -5.5,
        "stock_20d_pct": -0.96,
        "spread_regime": "중립",
        "safety_adjustment": 0,
        "pricing_power": 49.0,
        "raw_material_volatility_score": 57.5,
        "margin_safety_score": 6.38,
        "shock_analysis": {
          "windows": 0,
          "avg_stock_when_commodity_shock_pct": null
        },
        "vs_prior_month_avg_pct": -5.12
      }
    },
    "MKTX": {
      "sector": "Financial Services",
      "commodity_tickers": [
        "GC=F",
        "CL=F"
      ],
      "primary": {
        "commodity_ticker": "CL=F",
        "correlation_60d": 0.145,
        "commodity_20d_pct": -24.51,
        "stock_20d_pct": -13.83,
        "spread_regime": "동반 약세",
        "safety_adjustment": -5,
        "pricing_power": 77.5,
        "raw_material_volatility_score": 100.0,
        "margin_safety_score": 6.5,
        "shock_analysis": {
          "windows": 29,
          "avg_stock_when_commodity_shock_pct": -8.64
        },
        "vs_prior_month_avg_pct": -25.98
      }
    },
    "RRC": {
      "sector": "Energy",
      "commodity_tickers": [
        "CL=F",
        "NG=F"
      ],
      "primary": {
        "commodity_ticker": "NG=F",
        "correlation_60d": 0.4688,
        "commodity_20d_pct": 9.84,
        "stock_20d_pct": -10.31,
        "spread_regime": "최악의 상황",
        "safety_adjustment": -50,
        "pricing_power": 77.5,
        "raw_material_volatility_score": 100.0,
        "margin_safety_score": 6.5,
        "shock_analysis": {
          "windows": 37,
          "avg_stock_when_commodity_shock_pct": -3.34
        },
        "vs_prior_month_avg_pct": 8.72
      }
    },
    "THO": {
      "sector": "Consumer Cyclical",
      "commodity_tickers": [
        "CL=F",
        "ZC=F"
      ],
      "primary": {
        "commodity_ticker": "CL=F",
        "correlation_60d": -0.3592,
        "commodity_20d_pct": -24.51,
        "stock_20d_pct": -5.4,
        "spread_regime": "동반 약세",
        "safety_adjustment": -5,
        "pricing_power": 31.2,
        "raw_material_volatility_score": 100.0,
        "margin_safety_score": -21.25,
        "shock_analysis": {
          "windows": 29,
          "avg_stock_when_commodity_shock_pct": -4.92
        },
        "vs_prior_month_avg_pct": -25.98
      }
    },
    "NEM": {
      "sector": "Basic Materials",
      "commodity_tickers": [
        "HG=F",
        "LIT"
      ],
      "primary": {
        "commodity_ticker": "LIT",
        "correlation_60d": 0.6647,
        "commodity_20d_pct": -8.03,
        "stock_20d_pct": -8.89,
        "spread_regime": "동반 약세",
        "safety_adjustment": -5,
        "pricing_power": 77.5,
        "raw_material_volatility_score": 87.6,
        "margin_safety_score": 11.47,
        "shock_analysis": {
          "windows": 50,
          "avg_stock_when_commodity_shock_pct": 5.75
        },
        "vs_prior_month_avg_pct": -9.93
      }
    }
  },
  "mom_narratives": [
    {
      "commodity_ticker": "CL=F",
      "line": "CL=F는 전월 대비 25.98% 폭락, EOG는 CL=F와 강하게 연동돼 20일간 -4.48% 하락했지만 마진·가격결정력은 괜찮아. 나머지 종목들도 동반 약세 흐름이야.",
      "source": "gemini"
    },
    {
      "commodity_ticker": "GC=F",
      "line": "GC=F는 전월 평균 대비 10.28% 하락했어.",
      "source": "gemini"
    }
  ],
  "narrative_lines": [
    "CL=F는 전월 대비 25.98% 폭락, EOG는 CL=F와 강하게 연동돼 20일간 -4.48% 하락했지만 마진·가격결정력은 괜찮아. 나머지 종목들도 동반 약세 흐름이야.",
    "GC=F는 전월 평균 대비 10.28% 하락했어."
  ]
}