{
  "ok": true,
  "ok_count": 2,
  "total": 2,
  "total_supply_usd": 257655856280.25925,
  "usdt": {
    "ok": true,
    "total_supply_usd": 184309681989.74496,
    "by_chain": [
      {
        "chain": "ETH",
        "supply": 92062996230.90965
      },
      {
        "chain": "TRON",
        "supply": 90290450587.2953
      },
      {
        "chain": "SOL",
        "supply": 3839923637.879526
      },
      {
        "chain": "AVA",
        "supply": 1847205574.047338
      },
      {
        "chain": "TON",
        "supply": 1429976002.51
      },
      {
        "chain": "APTOS",
        "supply": 1229832921.984195
      },
      {
        "chain": "OMNI",
        "supply": 887961971.795665
      },
      {
        "chain": "NEAR",
        "supply": 525944120.793709
      },
      {
        "chain": "CELO",
        "supply": 470000000.997
      },
      {
        "chain": "KAIA",
        "supply": 249900001.0
      },
      {
        "chain": "COSMOS",
        "supply": 159997865.1663
      },
      {
        "chain": "TEZOS",
        "supply": 141000001.0
      }
    ],
    "chain_count": 18,
    "total_assets_usd": 189776623766.9662,
    "total_liabilities_usd": 184309681989.74496,
    "chain_sum_usd": 193406328525.28583,
    "as_of": null,
    "source": "Tether (tether.to)"
  },
  "usdc": {
    "ok": true,
    "total_supply_usd": 73346174290.51428,
    "by_chain": [
      {
        "chain": "ETH",
        "supply": 50535569639.63406
      },
      {
        "chain": "SOL",
        "supply": 7057653043.121219
      },
      {
        "chain": "HYPEREVM",
        "supply": 5608925702.091515
      },
      {
        "chain": "BASE",
        "supply": 4263177998.629271
      },
      {
        "chain": "ARB",
        "supply": 2556696246.735975
      },
      {
        "chain": "POLY",
        "supply": 652842275.356994
      },
      {
        "chain": "AVAX",
        "supply": 481677437.695432
      },
      {
        "chain": "SUI",
        "supply": 309154828.664581
      },
      {
        "chain": "XLM",
        "supply": 286501070.3233133
      },
      {
        "chain": "APTOS",
        "supply": 255653218.291416
      },
      {
        "chain": "MONAD",
        "supply": 245927047.282704
      },
      {
        "chain": "OP",
        "supply": 162048240.991408
      }
    ],
    "chain_count": 37,
    "as_of": "2026-07-11T22:59:17.497272Z",
    "source": "Circle (circle.com)"
  },
  "sources": [
    "Tether (tether.to)",
    "Circle (circle.com)"
  ],
  "collected_at": "2026-07-12T08:00:09+09:00",
  "schema_version": "v0",
  "diagnostics": {
    "ok_count": 2,
    "used_prev_snapshot": false
  }
}