{
  "ok": true,
  "source": "DefiLlama (defillama.com)",
  "protocols": [
    {
      "name": "Tether",
      "category": "Stablecoin Issuer",
      "chains": [
        "Off Chain"
      ],
      "fees_24h": 15995473.0,
      "fees_7d": 112581643.0,
      "revenue_24h": 15995473.0,
      "tvl": 0.0
    },
    {
      "name": "Circle USDC",
      "category": "Stablecoin Issuer",
      "chains": [
        "Ethereum",
        "Off Chain"
      ],
      "fees_24h": 6422805.0,
      "fees_7d": 45199613.0,
      "revenue_24h": 6422805.0,
      "tvl": 0.0
    },
    {
      "name": "Canton",
      "category": "Chain",
      "chains": [
        "Canton"
      ],
      "fees_24h": 1818153.0,
      "fees_7d": 12921332.0,
      "revenue_24h": 1818153.0,
      "tvl": 0.0
    },
    {
      "name": "Polymarket International",
      "category": "Prediction Market",
      "chains": [
        "Polygon"
      ],
      "fees_24h": 1539074.0,
      "fees_7d": 11074994.0,
      "revenue_24h": 1539074.0,
      "tvl": 440211634.0317645
    },
    {
      "name": "PumpSwap",
      "category": "Dexs",
      "chains": [
        "Solana"
      ],
      "fees_24h": 1335445.0,
      "fees_7d": 9084317.0,
      "revenue_24h": 211544.0,
      "tvl": 216726960.57221437
    },
    {
      "name": "Sky Lending",
      "category": "CDP",
      "chains": [
        "Ethereum"
      ],
      "fees_24h": 1033992.0,
      "fees_7d": 7077588.0,
      "revenue_24h": 478227.0,
      "tvl": 5612467063.877771
    },
    {
      "name": "Lido",
      "category": "Liquid Staking",
      "chains": [
        "Ethereum"
      ],
      "fees_24h": 1013735.0,
      "fees_7d": 7539904.0,
      "revenue_24h": 62509.0,
      "tvl": 14272917030.925632
    },
    {
      "name": "Hyperliquid Perps",
      "category": "Derivatives",
      "chains": [
        "Hyperliquid L1"
      ],
      "fees_24h": 914178.0,
      "fees_7d": 15535403.0,
      "revenue_24h": 677622.0,
      "tvl": 0.0
    },
    {
      "name": "Aave V3",
      "category": "Lending",
      "chains": [
        "Polygon",
        "Fantom",
        "Arbitrum",
        "Avalanche",
        "OP Mainnet",
        "Ethereum",
        "Metis",
        "Base",
        "Gnosis",
        "BSC",
        "Scroll",
        "ZKsync Era",
        "Linea",
        "Celo",
        "Sonic",
        "Soneium",
        "Plasma",
        "Mantle",
        "MegaETH",
        "X Layer"
      ],
      "fees_24h": 848489.0,
      "fees_7d": 7476623.0,
      "revenue_24h": 108652.0,
      "tvl": 11834723875.443462
    },
    {
      "name": "Hyper Foundation HYPE Staking",
      "category": "Staking Pool",
      "chains": [
        "Hyperliquid L1"
      ],
      "fees_24h": 806608.0,
      "fees_7d": 5889150.0,
      "revenue_24h": 24198.0,
      "tvl": 0.0
    },
    {
      "name": "Fragment",
      "category": "NFT Marketplace",
      "chains": [
        "TON"
      ],
      "fees_24h": 782284.0,
      "fees_7d": 5898886.0,
      "revenue_24h": -99064.0,
      "tvl": 0.0
    },
    {
      "name": "Tron",
      "category": "Chain",
      "chains": [
        "Tron"
      ],
      "fees_24h": 728961.0,
      "fees_7d": 5811995.0,
      "revenue_24h": 728961.0,
      "tvl": 0.0
    },
    {
      "name": "pump.fun",
      "category": "Launchpad",
      "chains": [
        "Solana"
      ],
      "fees_24h": 673382.0,
      "fees_7d": 5208788.0,
      "revenue_24h": 516393.0,
      "tvl": 0.0
    },
    {
      "name": "Paxos Stablecoin Issuer",
      "category": "Stablecoin Issuer",
      "chains": [
        "Off Chain"
      ],
      "fees_24h": 569798.0,
      "fees_7d": 3967140.0,
      "revenue_24h": 280242.0,
      "tvl": 0.0
    },
    {
      "name": "Collector Crypt",
      "category": "Physical TCG",
      "chains": [
        "Solana"
      ],
      "fees_24h": 530031.0,
      "fees_7d": 3702950.0,
      "revenue_24h": 530031.0,
      "tvl": 0.0
    },
    {
      "name": "Morpho Blue",
      "category": "Lending",
      "chains": [
        "Ethereum",
        "Base",
        "Arbitrum",
        "OP Mainnet",
        "Polygon",
        "Fraxtal",
        "Scroll",
        "World Chain",
        "Ink",
        "Unichain",
        "Hemi",
        "Sonic",
        "Corn",
        "Mode",
        "Hyperliquid L1",
        "Soneium",
        "Zircuit",
        "Katana",
        "Monad",
        "Stable",
        "Celo",
        "Plume Mainnet",
        "Abstract",
        "Flare",
        "Citrea",
        "Tempo",
        "Etherlink"
      ],
      "fees_24h": 455074.0,
      "fees_7d": 4325309.0,
      "revenue_24h": 0.0,
      "tvl": 6558923409.40916
    },
    {
      "name": "Grayscale",
      "category": "RWA",
      "chains": [
        "Off Chain"
      ],
      "fees_24h": 447048.0,
      "fees_7d": 3264280.0,
      "revenue_24h": 447048.0,
      "tvl": 0.0
    },
    {
      "name": "Binance staked ETH",
      "category": "Liquid Staking",
      "chains": [
        "BSC",
        "Ethereum"
      ],
      "fees_24h": 433700.0,
      "fees_7d": 2659986.0,
      "revenue_24h": 43370.0,
      "tvl": 5809723283.082616
    },
    {
      "name": "World Liberty Financial",
      "category": "Lending",
      "chains": [
        "Off Chain"
      ],
      "fees_24h": 400791.0,
      "fees_7d": 2855175.0,
      "revenue_24h": 400791.0,
      "tvl": 0.0
    },
    {
      "name": "Uniswap V4",
      "category": "Dexs",
      "chains": [
        "Ethereum",
        "Unichain",
        "OP Mainnet",
        "Base",
        "Arbitrum",
        "Polygon",
        "Blast",
        "Zora",
        "World Chain",
        "Ink",
        "Soneium",
        "Avalanche",
        "BSC",
        "Monad",
        "X Layer"
      ],
      "fees_24h": 395229.0,
      "fees_7d": 3232353.0,
      "revenue_24h": 0.0,
      "tvl": 955411379.8471508
    },
    {
      "name": "Axiom",
      "category": "Trading App",
      "chains": [
        "Solana",
        "BSC"
      ],
      "fees_24h": 378300.0,
      "fees_7d": 2778638.0,
      "revenue_24h": 178197.0,
      "tvl": 0.0
    },
    {
      "name": "Meteora DLMM",
      "category": "Dexs",
      "chains": [
        "Solana"
      ],
      "fees_24h": 368082.0,
      "fees_7d": 2364826.0,
      "revenue_24h": 42419.0,
      "tvl": 191680060.05634695
    },
    {
      "name": "BSC",
      "category": "Chain",
      "chains": [
        "BSC"
      ],
      "fees_24h": 352795.0,
      "fees_7d": 3179263.0,
      "revenue_24h": 35279.0,
      "tvl": 0.0
    },
    {
      "name": "Solana",
      "category": "Chain",
      "chains": [
        "Solana"
      ],
      "fees_24h": 343906.0,
      "fees_7d": 2576056.0,
      "revenue_24h": 48063.0,
      "tvl": 0.0
    },
    {
      "name": "Spark Liquidity Layer",
      "category": "Onchain Capital Allocator",
      "chains": [
        "Ethereum"
      ],
      "fees_24h": 314612.0,
      "fees_7d": 1672185.0,
      "revenue_24h": 24467.0,
      "tvl": 2011697743.9098573
    }
  ],
  "chains": [
    {
      "name": "Ethereum",
      "tvl": 37397943460.19563
    },
    {
      "name": "BSC",
      "tvl": 4839870344.409928
    },
    {
      "name": "Solana",
      "tvl": 4803361350.07928
    },
    {
      "name": "Tron",
      "tvl": 4440336976.70147
    },
    {
      "name": "Base",
      "tvl": 4081994750.704932
    },
    {
      "name": "Bitcoin",
      "tvl": 3913570562.5824904
    },
    {
      "name": "Hyperliquid L1",
      "tvl": 1391076305.4516098
    },
    {
      "name": "Provenance",
      "tvl": 1347613725.9754605
    },
    {
      "name": "Arbitrum",
      "tvl": 1205043090.1963367
    },
    {
      "name": "Polygon",
      "tvl": 985081091.5980864
    },
    {
      "name": "Plasma",
      "tvl": 795144038.5389777
    },
    {
      "name": "Avalanche",
      "tvl": 459647729.7438099
    },
    {
      "name": "Sui",
      "tvl": 417266468.8467711
    },
    {
      "name": "Monad",
      "tvl": 366422112.30914664
    },
    {
      "name": "OP Mainnet",
      "tvl": 284671332.32710725
    },
    {
      "name": "Cronos",
      "tvl": 258844631.0687188
    },
    {
      "name": "Stellar",
      "tvl": 202525432.3695767
    },
    {
      "name": "Starknet",
      "tvl": 174861246.57252145
    },
    {
      "name": "Mantle",
      "tvl": 147311957.76219445
    },
    {
      "name": "Near",
      "tvl": 139227066.56521344
    },
    {
      "name": "Ink",
      "tvl": 128054014.61157306
    },
    {
      "name": "Movement",
      "tvl": 121768813.45515049
    },
    {
      "name": "Flare",
      "tvl": 116278070.40700898
    },
    {
      "name": "Aptos",
      "tvl": 110154936.60336716
    },
    {
      "name": "MegaETH",
      "tvl": 101312224.10522039
    }
  ],
  "counts": {
    "fee_protocols_total": 2340,
    "revenue_protocols_total": 1982,
    "chains_total": 453,
    "tvl_map_size": 7742
  },
  "collected_at": "2026-06-29T05:21:06+09:00",
  "schema_version": "v0",
  "diagnostics": {
    "protocols": 25,
    "used_prev_snapshot": false
  }
}