{
  "source": "bybit+okx",
  "btc": {
    "oi_okx_usd": 2013357736.5876095,
    "oi_okx_coin": 30510.967700000147,
    "oi_okx_contracts": 3051096.7700000145,
    "oi_okx_ts": "1784759563097",
    "long_short_ratio_okx": 1.27,
    "ls_ts_okx": "1784757600000",
    "long_short_ratio": 1.27,
    "oi_combined_usd": 2013357736.5876095,
    "ok": true,
    "as_of": "1784759563097"
  },
  "eth": {
    "oi_okx_usd": 1491061184.8914657,
    "oi_okx_coin": 770841.1620000029,
    "oi_okx_contracts": 7708411.620000029,
    "oi_okx_ts": "1784759563797",
    "long_short_ratio_okx": 1.2,
    "ls_ts_okx": "1784757600000",
    "long_short_ratio": 1.2,
    "oi_combined_usd": 1491061184.8914657,
    "ok": true,
    "as_of": "1784759563797"
  },
  "ok_count": 2,
  "ok": true,
  "collected_at": "2026-07-23T07:32:44+09:00",
  "schema_version": "v0",
  "diagnostics": {
    "ok_count": 2,
    "used_prev_snapshot": false
  }
}