{
  "updated_at": "2026-05-19T01:01:38+09:00",
  "elapsed_sec": 13.09,
  "indices": {
    "kospi": {
      "value": 7516.04,
      "change_pct": 0.31,
      "symbol": "^KS11"
    },
    "kosdaq": {
      "value": 1111.09,
      "change_pct": -1.66,
      "symbol": "^KQ11"
    },
    "sp500": {
      "value": 7378.080078125,
      "change_pct": -0.42,
      "symbol": "^GSPC"
    },
    "nasdaq": {
      "value": 26008.75390625,
      "change_pct": -0.83,
      "symbol": "^IXIC"
    },
    "dow": {
      "value": 49498.19921875,
      "change_pct": -0.07,
      "symbol": "^DJI"
    },
    "vix": {
      "value": 18.700000762939453,
      "change_pct": 1.52,
      "symbol": "^VIX"
    },
    "usdkrw": {
      "value": 1494.6199951171875,
      "change_pct": -0.21,
      "symbol": "KRW=X"
    }
  },
  "prices": {
    "000240": 24050.0,
    "035420": 200000.0,
    "035900": 59000.0,
    "041510": 73300.0,
    "100840": 44400.0,
    "175330": 25250.0,
    "200670": 33950.0,
    "214150": 48500.0,
    "214450": 141300.0,
    "BAC": 50.505001068115234,
    "CRM": 177.77000427246094,
    "DIS": 103.83499908447266,
    "QCOM": 197.24000549316406,
    "TMO": 440.42498779296875,
    "XOM": 160.27999877929688,
    "META": 606.885009765625,
    "BRK-B": 483.4100036621094,
    "PG": 142.2899932861328,
    "MSFT": 418.3900146484375,
    "JPM": 299.8924865722656,
    "SOFI": 15.585000038146973,
    "JNJ": 227.69749450683594,
    "CSCO": 116.54499816894531,
    "ADBE": 252.1649932861328
  },
  "counts": {
    "indices": 7,
    "kr": 9,
    "us": 15,
    "kr_requested": 10,
    "us_requested": 15
  }
}