{
  "updated_at": "2026-07-01T00:12:56+09:00",
  "elapsed_sec": 43.66,
  "indices": {
    "kospi": {
      "value": 8476.48,
      "change_pct": 0.97,
      "symbol": "^KS11"
    },
    "kosdaq": {
      "value": 916.18,
      "change_pct": -0.48,
      "symbol": "^KQ11"
    },
    "sp500": {
      "value": 7472.72998046875,
      "change_pct": 0.43,
      "symbol": "^GSPC"
    },
    "nasdaq": {
      "value": 26043.251953125,
      "change_pct": 0.86,
      "symbol": "^IXIC"
    },
    "dow": {
      "value": 52312.890625,
      "change_pct": 0.25,
      "symbol": "^DJI"
    },
    "vix": {
      "value": 17.110000610351562,
      "change_pct": -3.06,
      "symbol": "^VIX"
    },
    "usdkrw": {
      "value": 1551.0,
      "change_pct": 0.58,
      "symbol": "KRW=X"
    }
  },
  "prices": {
    "000240": 23700.0,
    "000270": 138000.0,
    "003550": 97300.0,
    "009540": 350000.0,
    "035420": 199000.0,
    "064350": 173000.0,
    "100840": 28250.0,
    "114090": 10320.0,
    "204610": 1187.0,
    "214150": 48500.0,
    "214450": 141300.0,
    "CME": 222.90499877929688,
    "IVZ": 26.440000534057617,
    "EQT": 53.25,
    "KHC": 24.059999465942383,
    "ALB": 134.25999450683594,
    "LEN": 91.3499984741211,
    "CHRD": 116.84500122070312,
    "CAG": 13.625,
    "CTSH": 37.329898834228516,
    "RRC": 36.9900016784668,
    "MKC": 50.599998474121094,
    "EOG": 132.02000427246094,
    "NEM": 92.95999908447266,
    "PLAB": 32.36000061035156,
    "EXE": 92.41500091552734,
    "INGR": 94.83999633789062,
    "MGY": 25.940000534057617,
    "HLNE": 76.63999938964844,
    "ACN": 122.70999908447266,
    "VSNT": 35.56999969482422,
    "CALM": 79.87000274658203
  },
  "counts": {
    "indices": 7,
    "kr": 11,
    "us": 21,
    "kr_requested": 11,
    "us_requested": 21
  }
}