{
  "updated_at": "2026-07-08T04:37:32+09:00",
  "elapsed_sec": 15.72,
  "indices": {
    "kospi": {
      "value": 7656.31,
      "change_pct": -4.91,
      "symbol": "^KS11"
    },
    "kosdaq": {
      "value": 831.23,
      "change_pct": -1.87,
      "symbol": "^KQ11"
    },
    "sp500": {
      "value": 7493.9599609375,
      "change_pct": -0.59,
      "symbol": "^GSPC"
    },
    "nasdaq": {
      "value": 25786.310546875,
      "change_pct": -1.28,
      "symbol": "^IXIC"
    },
    "dow": {
      "value": 52850.0703125,
      "change_pct": -0.4,
      "symbol": "^DJI"
    },
    "vix": {
      "value": 16.329999923706055,
      "change_pct": 4.95,
      "symbol": "^VIX"
    },
    "usdkrw": {
      "value": 1513.050048828125,
      "change_pct": -1.1,
      "symbol": "KRW=X"
    }
  },
  "prices": {
    "003550": 102300.0,
    "009540": 360500.0,
    "035420": 197200.0,
    "035900": 54400.0,
    "064350": 186400.0,
    "064400": 74000.0,
    "100840": 25600.0,
    "114090": 10520.0,
    "204610": 2970.0,
    "214150": 47750.0,
    "214450": 340500.0,
    "483650": 230000.0,
    "RRC": 37.91999816894531,
    "VSNT": 37.20000076293945,
    "HLNE": 80.56999969482422,
    "ACN": 143.11000061035156,
    "FSLR": 228.33999633789062,
    "ALB": 128.88999938964844,
    "MLI": 55.41999816894531,
    "NEM": 94.73500061035156,
    "LEN": 86.47000122070312,
    "CHRD": 117.13500213623047,
    "CAG": 14.164999961853027,
    "EXE": 89.74500274658203,
    "EQT": 51.880001068115234,
    "MKTX": 118.8499984741211,
    "EPAM": 90.30000305175781,
    "INGR": 98.55500030517578,
    "CTSH": 43.779998779296875,
    "EOG": 134.64999389648438
  },
  "counts": {
    "indices": 7,
    "kr": 12,
    "us": 18,
    "kr_requested": 12,
    "us_requested": 18
  }
}