{
  "updated_at": "2026-05-21T01:06:42+09:00",
  "elapsed_sec": 18.53,
  "indices": {
    "kospi": {
      "value": 7208.95,
      "change_pct": -0.86,
      "symbol": "^KS11"
    },
    "kosdaq": {
      "value": 1056.07,
      "change_pct": -2.61,
      "symbol": "^KQ11"
    },
    "sp500": {
      "value": 7422.31005859375,
      "change_pct": 0.92,
      "symbol": "^GSPC"
    },
    "nasdaq": {
      "value": 26214.732421875,
      "change_pct": 1.33,
      "symbol": "^IXIC"
    },
    "dow": {
      "value": 49875.1015625,
      "change_pct": 1.02,
      "symbol": "^DJI"
    },
    "vix": {
      "value": 17.639999389648438,
      "change_pct": -2.38,
      "symbol": "^VIX"
    },
    "usdkrw": {
      "value": 1497.0799560546875,
      "change_pct": -0.65,
      "symbol": "KRW=X"
    }
  },
  "prices": {
    "035420": 191500.0,
    "035900": 59000.0,
    "041510": 73300.0,
    "064350": 190500.0,
    "071050": 232500.0,
    "100840": 40900.0,
    "175330": 24950.0,
    "200670": 33950.0,
    "214150": 48500.0,
    "214450": 141300.0,
    "ADBE": 250.24000549316406,
    "GOOGL": 386.1549987792969,
    "BAC": 51.3650016784668,
    "QCOM": 200.75,
    "DIS": 104.19000244140625,
    "JPM": 301.8699951171875,
    "META": 605.375,
    "XOM": 158.72999572753906,
    "JNJ": 229.77999877929688,
    "PG": 142.97000122070312,
    "CRM": 177.6300048828125,
    "MSFT": 417.8999938964844,
    "TMO": 444.07501220703125,
    "BRK-B": 480.010009765625,
    "SOFI": 15.614999771118164,
    "CSCO": 115.69000244140625
  },
  "counts": {
    "indices": 7,
    "kr": 10,
    "us": 16,
    "kr_requested": 10,
    "us_requested": 16
  }
}