{
  "updated_at": "2026-07-02T00:22:30+09:00",
  "elapsed_sec": 15.73,
  "indices": {
    "kospi": {
      "value": 8303.41,
      "change_pct": -2.04,
      "symbol": "^KS11"
    },
    "kosdaq": {
      "value": 929.35,
      "change_pct": 1.44,
      "symbol": "^KQ11"
    },
    "sp500": {
      "value": 7516.83984375,
      "change_pct": 0.23,
      "symbol": "^GSPC"
    },
    "nasdaq": {
      "value": 26218.30859375,
      "change_pct": 0.02,
      "symbol": "^IXIC"
    },
    "dow": {
      "value": 52459.98046875,
      "change_pct": 0.27,
      "symbol": "^DJI"
    },
    "vix": {
      "value": 16.25,
      "change_pct": -1.22,
      "symbol": "^VIX"
    },
    "usdkrw": {
      "value": 1550.719970703125,
      "change_pct": 0.33,
      "symbol": "KRW=X"
    }
  },
  "prices": {
    "000240": 24200.0,
    "000270": 141500.0,
    "003550": 96600.0,
    "009540": 358500.0,
    "013030": 32900.0,
    "035420": 197400.0,
    "064350": 189800.0,
    "064400": 76200.0,
    "100840": 29600.0,
    "114090": 10290.0,
    "204610": 2905.0,
    "214450": 366500.0,
    "VSNT": 36.540000915527344,
    "INGR": 95.80999755859375,
    "HLNE": 79.62000274658203,
    "RRC": 36.974998474121094,
    "CHRD": 112.73799896240234,
    "MKC": 52.290000915527344,
    "ACN": 130.55499267578125,
    "MGY": 25.155000686645508,
    "CME": 226.3699951171875,
    "NEM": 94.79499816894531,
    "CAG": 14.125,
    "EQT": 52.39849853515625,
    "KHC": 24.729999542236328,
    "EXE": 90.37000274658203,
    "CTSH": 40.64500045776367,
    "EOG": 128.22999572753906
  },
  "counts": {
    "indices": 7,
    "kr": 12,
    "us": 16,
    "kr_requested": 12,
    "us_requested": 16
  }
}