{
  "updated_at": "2026-06-26T02:16:56+09:00",
  "elapsed_sec": 10.54,
  "indices": {
    "kospi": {
      "value": 8930.3,
      "change_pct": 5.42,
      "symbol": "^KS11"
    },
    "kosdaq": {
      "value": 887.81,
      "change_pct": -2.36,
      "symbol": "^KQ11"
    },
    "sp500": {
      "value": 7367.1201171875,
      "change_pct": 0.1,
      "symbol": "^GSPC"
    },
    "nasdaq": {
      "value": 25395.91015625,
      "change_pct": -0.32,
      "symbol": "^IXIC"
    },
    "dow": {
      "value": 52074.3203125,
      "change_pct": 0.42,
      "symbol": "^DJI"
    },
    "vix": {
      "value": 19.1299991607666,
      "change_pct": 2.57,
      "symbol": "^VIX"
    },
    "usdkrw": {
      "value": 1542.22998046875,
      "change_pct": 0.17,
      "symbol": "KRW=X"
    }
  },
  "prices": {
    "VSNT": 36.779998779296875,
    "CHRD": 119.4800033569336,
    "THO": 77.87999725341797,
    "KHC": 23.603099822998047,
    "EQT": 51.079498291015625,
    "EOG": 133.02999877929688,
    "NEM": 96.08999633789062,
    "RRC": 36.09000015258789,
    "INGR": 97.06999969482422,
    "ALB": 141.82000732421875,
    "LEN": 94.18000030517578,
    "HLNE": 75.80000305175781,
    "EXE": 88.33000183105469,
    "MKC": 49.54999923706055,
    "ACN": 126.77010345458984,
    "CTSH": 39.375,
    "CAG": 13.795000076293945
  },
  "counts": {
    "indices": 7,
    "kr": 0,
    "us": 17,
    "kr_requested": 0,
    "us_requested": 17
  }
}