{
  "updated_at": "2026-06-25T02:47:19+09:00",
  "elapsed_sec": 43.52,
  "indices": {
    "kospi": {
      "value": 8471.02,
      "change_pct": 3.26,
      "symbol": "^KS11"
    },
    "kosdaq": {
      "value": 909.31,
      "change_pct": 2.0,
      "symbol": "^KQ11"
    },
    "sp500": {
      "value": 7347.2099609375,
      "change_pct": -0.25,
      "symbol": "^GSPC"
    },
    "nasdaq": {
      "value": 25478.505859375,
      "change_pct": -0.42,
      "symbol": "^IXIC"
    },
    "dow": {
      "value": 51754.03125,
      "change_pct": 0.17,
      "symbol": "^DJI"
    },
    "vix": {
      "value": 20.15999984741211,
      "change_pct": 3.49,
      "symbol": "^VIX"
    },
    "usdkrw": {
      "value": 1543.4200439453125,
      "change_pct": 0.84,
      "symbol": "KRW=X"
    }
  },
  "prices": {
    "000270": 138900.0,
    "003550": 99200.0,
    "009540": 368000.0,
    "028050": 43950.0,
    "035420": 199400.0,
    "035900": 59000.0,
    "086280": 189100.0,
    "100840": 28850.0,
    "114090": 10880.0,
    "214450": 141300.0,
    "KHC": 22.985000610351562,
    "ALB": 146.91000366210938,
    "THO": 76.27999877929688,
    "CAG": 13.59000015258789,
    "MKTX": 114.61000061035156,
    "ACN": 129.63999938964844,
    "RRC": 36.3650016784668,
    "EXE": 88.23999786376953,
    "VSNT": 38.17580032348633,
    "CTSH": 41.97999954223633,
    "EOG": 133.9199981689453,
    "NEM": 93.30000305175781,
    "INGR": 97.91999816894531,
    "HLNE": 74.25,
    "EQT": 51.68000030517578,
    "LEN": 92.3949966430664
  },
  "counts": {
    "indices": 7,
    "kr": 10,
    "us": 16,
    "kr_requested": 10,
    "us_requested": 16
  }
}