{
  "updated_at": "2026-05-21T04:07:02+09:00",
  "elapsed_sec": 8.78,
  "indices": {
    "kospi": {
      "value": 7208.95,
      "change_pct": -0.86,
      "symbol": "^KS11"
    },
    "kosdaq": {
      "value": 1056.07,
      "change_pct": -2.61,
      "symbol": "^KQ11"
    },
    "sp500": {
      "value": 7421.6201171875,
      "change_pct": 0.91,
      "symbol": "^GSPC"
    },
    "nasdaq": {
      "value": 26205.525390625,
      "change_pct": 1.29,
      "symbol": "^IXIC"
    },
    "dow": {
      "value": 49966.76171875,
      "change_pct": 1.2,
      "symbol": "^DJI"
    },
    "vix": {
      "value": 17.540000915527344,
      "change_pct": -2.93,
      "symbol": "^VIX"
    },
    "usdkrw": {
      "value": 1496.8399658203125,
      "change_pct": -0.66,
      "symbol": "KRW=X"
    }
  },
  "prices": {
    "035420": 191500.0,
    "035900": 59500.0,
    "041510": 84400.0,
    "064350": 190500.0,
    "071050": 232500.0,
    "100840": 40900.0,
    "175330": 24950.0,
    "200670": 28700.0,
    "214150": 46550.0,
    "214450": 295000.0,
    "TMO": 448.17498779296875,
    "JNJ": 230.58999633789062,
    "CRM": 177.76800537109375,
    "CSCO": 114.2699966430664,
    "BAC": 51.21500015258789,
    "DIS": 104.45999908447266,
    "GOOGL": 386.8399963378906,
    "QCOM": 203.2100067138672,
    "ADBE": 251.3000030517578,
    "XOM": 157.9600067138672,
    "JPM": 302.2099914550781,
    "SOFI": 15.534099578857422,
    "MSFT": 419.4700012207031,
    "META": 603.280029296875,
    "PG": 142.83999633789062,
    "BRK-B": 480.1199951171875
  },
  "counts": {
    "indices": 7,
    "kr": 10,
    "us": 16,
    "kr_requested": 10,
    "us_requested": 16
  }
}