{"status": "000", "message": "정상", "list": [{"rcept_no": "20160330003977", "reprt_code": "11011", "bsns_year": "2015", "corp_code": "00126371", "stock_code": "009150", "fs_div": "CFS", "fs_nm": "연결재무제표", "sj_div": "BS", "sj_nm": "재무상태표", "account_nm": "유동자산", "thstrm_nm": "제 43 기", "thstrm_dt": "2015.12.31 현재", "thstrm_amount": "2,729,971,297,487", "frmtrm_nm": "제 42 기", "frmtrm_dt": "2014.12.31 현재", "frmtrm_amount": "3,553,986,684,611", "bfefrmtrm_nm": "제 41 기", "bfefrmtrm_dt": "2013.12.31 현재", "bfefrmtrm_amount": "2,650,765,404,781", "ord": "1", "currency": "KRW"}, {"rcept_no": "20160330003977", "reprt_code": "11011", "bsns_year": "2015", "corp_code": "00126371", "stock_code": "009150", "fs_div": "CFS", "fs_nm": "연결재무제표", "sj_div": "BS", "sj_nm": "재무상태표", "account_nm": "비유동자산", "thstrm_nm": "제 43 기", "thstrm_dt": "2015.12.31 현재", "thstrm_amount": "4,539,481,565,715", "frmtrm_nm": "제 42 기", "frmtrm_dt": "2014.12.31 현재", "frmtrm_amount": "4,164,625,300,504", "bfefrmtrm_nm": "제 41 기", "bfefrmtrm_dt": "2013.12.31 현재", "bfefrmtrm_amount": "4,534,577,572,799", "ord": "3", "currency": "KRW"}, {"rcept_no": "20160330003977", "reprt_code": "11011", "bsns_year": "2015", "corp_code": "00126371", "stock_code": "009150", "fs_div": "CFS", "fs_nm": "연결재무제표", "sj_div": "BS", "sj_nm": "재무상태표", "account_nm": "자산총계", "thstrm_nm": "제 43 기", "thstrm_dt": "2015.12.31 현재", "thstrm_amount": "7,269,452,863,202", "frmtrm_nm": "제 42 기", "frmtrm_dt": "2014.12.31 현재", "frmtrm_amount": "7,718,611,985,115", "bfefrmtrm_nm": "제 41 기", "bfefrmtrm_dt": "2013.12.31 현재", "bfefrmtrm_amount": "7,185,342,977,580", "ord": "5", "currency": "KRW"}, {"rcept_no": "20160330003977", "reprt_code": "11011", "bsns_year": "2015", "corp_code": "00126371", "stock_code": "009150", "fs_div": "CFS", "fs_nm": "연결재무제표", "sj_div": "BS", "sj_nm": "재무상태표", "account_nm": "유동부채", "thstrm_nm": "제 43 기", "thstrm_dt": "2015.12.31 현재", "thstrm_amount": "1,768,254,033,682", "frmtrm_nm": "제 42 기", "frmtrm_dt": "2014.12.31 현재", "frmtrm_amount": "2,151,001,955,898", "bfefrmtrm_nm": "제 41 기", "bfefrmtrm_dt": "2013.12.31 현재", "bfefrmtrm_amount": "1,787,431,593,746", "ord": "7", "currency": "KRW"}, {"rcept_no": "20160330003977", "reprt_code": "11011", "bsns_year": "2015", "corp_code": "00126371", "stock_code": "009150", "fs_div": "CFS", "fs_nm": "연결재무제표", "sj_div": "BS", "sj_nm": "재무상태표", "account_nm": "비유동부채", "thstrm_nm": "제 43 기", "thstrm_dt": "2015.12.31 현재", "thstrm_amount": "1,185,815,611,607", "frmtrm_nm": "제 42 기", "frmtrm_dt": "2014.12.31 현재", "frmtrm_amount": "924,813,949,065", "bfefrmtrm_nm": "제 41 기", "bfefrmtrm_dt": "2013.12.31 현재", "bfefrmtrm_amount": "1,139,883,944,868", "ord": "9", "currency": "KRW"}, {"rcept_no": "20160330003977", "reprt_code": "11011", "bsns_year": "2015", "corp_code": "00126371", "stock_code": "009150", "fs_div": "CFS", "fs_nm": "연결재무제표", "sj_div": "BS", "sj_nm": "재무상태표", "account_nm": "부채총계", "thstrm_nm": "제 43 기", "thstrm_dt": "2015.12.31 현재", "thstrm_amount": "2,954,069,645,289", "frmtrm_nm": "제 42 기", "frmtrm_dt": "2014.12.31 현재", "frmtrm_amount": "3,075,815,904,963", "bfefrmtrm_nm": "제 41 기", "bfefrmtrm_dt": "2013.12.31 현재", "bfefrmtrm_amount": "2,927,315,538,614", "ord": "11", "currency": "KRW"}, {"rcept_no": "20160330003977", "reprt_code": "11011", "bsns_year": "2015", "corp_code": "00126371", "stock_code": "009150", "fs_div": "CFS", "fs_nm": "연결재무제표", "sj_div": "BS", "sj_nm": "재무상태표", "account_nm": "자본총계", "thstrm_nm": "제 43 기", "thstrm_dt": "2015.12.31 현재", "thstrm_amount": "4,315,383,217,913", "frmtrm_nm": "제 42 기", "frmtrm_dt": "2014.12.31 현재", "frmtrm_amount": "4,642,796,080,152", "bfefrmtrm_nm": "제 41 기", "bfefrmtrm_dt": "2013.12.31 현재", "bfefrmtrm_amount": "4,258,027,438,966", "ord": "21", "currency": "KRW"}, {"rcept_no": "20160330003977", "reprt_code": "11011", "bsns_year": "2015", "corp_code": "00126371", "stock_code": "009150", "fs_div": "CFS", "fs_nm": "연결재무제표", "sj_div": "IS", "sj_nm": "손익계산서", "account_nm": "매출액", "thstrm_nm": "제 43 기", "thstrm_dt": "2015.01.01 ~ 2015.12.31", "thstrm_amount": "6,176,258,143,768", "frmtrm_nm": "제 42 기", "frmtrm_dt": "2014.01.01 ~ 2014.12.31", "frmtrm_amount": "6,100,447,147,864", "bfefrmtrm_nm": "제 41 기", "bfefrmtrm_dt": "2013.01.01 ~ 2013.12.31", "bfefrmtrm_amount": "7,126,507,233,616", "ord": "23", "currency": "KRW"}, {"rcept_no": "20160330003977", "reprt_code": "11011", "bsns_year": "2015", "corp_code": "00126371", "stock_code": "009150", "fs_div": "CFS", "fs_nm": "연결재무제표", "sj_div": "IS", "sj_nm": "손익계산서", "account_nm": "영업이익", "thstrm_nm": "제 43 기", "thstrm_dt": "2015.01.01 ~ 2015.12.31", "thstrm_amount": "301,331,565,461", "frmtrm_nm": "제 42 기", "frmtrm_dt": "2014.01.01 ~ 2014.12.31", "frmtrm_amount": "64,948,969,155", "bfefrmtrm_nm": "제 41 기", "bfefrmtrm_dt": "2013.01.01 ~ 2013.12.31", "bfefrmtrm_amount": "540,968,464,217", "ord": "25", "currency": "KRW"}, {"rcept_no": "20160330003977", "reprt_code": "11011", "bsns_year": "2015", "corp_code": "00126371", "stock_code": "009150", "fs_div": "CFS", "fs_nm": "연결재무제표", "sj_div": "IS", "sj_nm": "손익계산서", "account_nm": "법인세차감전 순이익", "thstrm_nm": "제 43 기", "thstrm_dt": "2015.01.01 ~ 2015.12.31", "thstrm_amount": "366,791,153,598", "frmtrm_nm": "제 42 기", "frmtrm_dt": "2014.01.01 ~ 2014.12.31", "frmtrm_amount": "816,239,202,628", "bfefrmtrm_nm": "제 41 기", "bfefrmtrm_dt": "2013.01.01 ~ 2013.12.31", "bfefrmtrm_amount": "514,865,044,866", "ord": "27", "currency": "KRW"}, {"rcept_no": "20160330003977", "reprt_code": "11011", "bsns_year": "2015", "corp_code": "00126371", "stock_code": "009150", "fs_div": "CFS", "fs_nm": "연결재무제표", "sj_div": "IS", "sj_nm": "손익계산서", "account_nm": "당기순이익(손실)", "thstrm_nm": "제 43 기", "thstrm_dt": "2015.01.01 ~ 2015.12.31", "thstrm_amount": "20,643,329,453", "frmtrm_nm": "제 42 기", "frmtrm_dt": "2014.01.01 ~ 2014.12.31", "frmtrm_amount": "508,911,818,142", "bfefrmtrm_nm": "제 41 기", "bfefrmtrm_dt": "2013.01.01 ~ 2013.12.31", "bfefrmtrm_amount": "345,692,360,329", "ord": "29", "currency": "KRW"}, {"rcept_no": "20160330003977", "reprt_code": "11011", "bsns_year": "2015", "corp_code": "00126371", "stock_code": "009150", "fs_div": "CFS", "fs_nm": "연결재무제표", "sj_div": "IS", "sj_nm": "손익계산서", "account_nm": "당기순이익(손실)", "thstrm_nm": "제 43 기", "thstrm_dt": "2015.01.01 ~ 2015.12.31", "thstrm_amount": "20,643,329,453", "frmtrm_nm": "제 42 기", "frmtrm_dt": "2014.01.01 ~ 2014.12.31", "frmtrm_amount": "508,911,818,142", "bfefrmtrm_nm": "제 41 기", "bfefrmtrm_dt": "2013.01.01 ~ 2013.12.31", "bfefrmtrm_amount": "345,692,360,329", "ord": "61", "currency": "KRW"}, {"rcept_no": "20160330003977", "reprt_code": "11011", "bsns_year": "2015", "corp_code": "00126371", "stock_code": "009150", "fs_div": "OFS", "fs_nm": "재무제표", "sj_div": "BS", "sj_nm": "재무상태표", "account_nm": "유동자산", "thstrm_nm": "제 43 기", "thstrm_dt": "2015.12.31 현재", "thstrm_amount": "2,025,557,321,811", "frmtrm_nm": "제 42 기", "frmtrm_dt": "2014.12.31 현재", "frmtrm_amount": "2,600,705,575,247", "bfefrmtrm_nm": "제 41 기", "bfefrmtrm_dt": "2013.12.31 현재", "bfefrmtrm_amount": "1,811,939,938,993", "ord": "2", "currency": "KRW"}, {"rcept_no": "20160330003977", "reprt_code": "11011", "bsns_year": "2015", "corp_code": "00126371", "stock_code": "009150", "fs_div": "OFS", "fs_nm": "재무제표", "sj_div": "BS", "sj_nm": "재무상태표", "account_nm": "비유동자산", "thstrm_nm": "제 43 기", "thstrm_dt": "2015.12.31 현재", "thstrm_amount": "3,297,287,991,926", "frmtrm_nm": "제 42 기", "frmtrm_dt": "2014.12.31 현재", "frmtrm_amount": "3,320,493,073,615", "bfefrmtrm_nm": "제 41 기", "bfefrmtrm_dt": "2013.12.31 현재", "bfefrmtrm_amount": "3,816,503,879,648", "ord": "4", "currency": "KRW"}, {"rcept_no": "20160330003977", "reprt_code": "11011", "bsns_year": "2015", "corp_code": "00126371", "stock_code": "009150", "fs_div": "OFS", "fs_nm": "재무제표", "sj_div": "BS", "sj_nm": "재무상태표", "account_nm": "자산총계", "thstrm_nm": "제 43 기", "thstrm_dt": "2015.12.31 현재", "thstrm_amount": "5,322,845,313,737", "frmtrm_nm": "제 42 기", "frmtrm_dt": "2014.12.31 현재", "frmtrm_amount": "5,921,198,648,862", "bfefrmtrm_nm": "제 41 기", "bfefrmtrm_dt": "2013.12.31 현재", "bfefrmtrm_amount": "5,628,443,818,641", "ord": "6", "currency": "KRW"}, {"rcept_no": "20160330003977", "reprt_code": "11011", "bsns_year": "2015", "corp_code": "00126371", "stock_code": "009150", "fs_div": "OFS", "fs_nm": "재무제표", "sj_div": "BS", "sj_nm": "재무상태표", "account_nm": "유동부채", "thstrm_nm": "제 43 기", "thstrm_dt": "2015.12.31 현재", "thstrm_amount": "809,825,373,490", "frmtrm_nm": "제 42 기", "frmtrm_dt": "2014.12.31 현재", "frmtrm_amount": "1,344,235,874,143", "bfefrmtrm_nm": "제 41 기", "bfefrmtrm_dt": "2013.12.31 현재", "bfefrmtrm_amount": "969,758,622,801", "ord": "8", "currency": "KRW"}, {"rcept_no": "20160330003977", "reprt_code": "11011", "bsns_year": "2015", "corp_code": "00126371", "stock_code": "009150", "fs_div": "OFS", "fs_nm": "재무제표", "sj_div": "BS", "sj_nm": "재무상태표", "account_nm": "비유동부채", "thstrm_nm": "제 43 기", "thstrm_dt": "2015.12.31 현재", "thstrm_amount": "446,919,502,688", "frmtrm_nm": "제 42 기", "frmtrm_dt": "2014.12.31 현재", "frmtrm_amount": "214,027,509,514", "bfefrmtrm_nm": "제 41 기", "bfefrmtrm_dt": "2013.12.31 현재", "bfefrmtrm_amount": "675,603,882,150", "ord": "10", "currency": "KRW"}, {"rcept_no": "20160330003977", "reprt_code": "11011", "bsns_year": "2015", "corp_code": "00126371", "stock_code": "009150", "fs_div": "OFS", "fs_nm": "재무제표", "sj_div": "BS", "sj_nm": "재무상태표", "account_nm": "부채총계", "thstrm_nm": "제 43 기", "thstrm_dt": "2015.12.31 현재", "thstrm_amount": "1,256,744,876,178", "frmtrm_nm": "제 42 기", "frmtrm_dt": "2014.12.31 현재", "frmtrm_amount": "1,558,263,383,657", "bfefrmtrm_nm": "제 41 기", "bfefrmtrm_dt": "2013.12.31 현재", "bfefrmtrm_amount": "1,645,362,504,951", "ord": "12", "currency": "KRW"}, {"rcept_no": "20160330003977", "reprt_code": "11011", "bsns_year": "2015", "corp_code": "00126371", "stock_code": "009150", "fs_div": "OFS", "fs_nm": "재무제표", "sj_div": "BS", "sj_nm": "재무상태표", "account_nm": "자본금", "thstrm_nm": "제 43 기", "thstrm_dt": "2015.12.31 현재", "thstrm_amount": "388,003,400,000", "frmtrm_nm": "제 42 기", "frmtrm_dt": "2014.12.31 현재", "frmtrm_amount": "388,003,400,000", "bfefrmtrm_nm": "제 41 기", "bfefrmtrm_dt": "2013.12.31 현재", "bfefrmtrm_amount": "388,003,400,000", "ord": "15", "currency": "KRW"}, {"rcept_no": "20160330003977", "reprt_code": "11011", "bsns_year": "2015", "corp_code": "00126371", "stock_code": "009150", "fs_div": "OFS", "fs_nm": "재무제표", "sj_div": "BS", "sj_nm": "재무상태표", "account_nm": "자본총계", "thstrm_nm": "제 43 기", "thstrm_dt": "2015.12.31 현재", "thstrm_amount": "4,066,100,437,559", "frmtrm_nm": "제 42 기", "frmtrm_dt": "2014.12.31 현재", "frmtrm_amount": "4,362,935,265,205", "bfefrmtrm_nm": "제 41 기", "bfefrmtrm_dt": "2013.12.31 현재", "bfefrmtrm_amount": "3,983,081,313,690", "ord": "22", "currency": "KRW"}, {"rcept_no": "20160330003977", "reprt_code": "11011", "bsns_year": "2015", "corp_code": "00126371", "stock_code": "009150", "fs_div": "OFS", "fs_nm": "재무제표", "sj_div": "IS", "sj_nm": "손익계산서", "account_nm": "매출액", "thstrm_nm": "제 43 기", "thstrm_dt": "2015.01.01 ~ 2015.12.31", "thstrm_amount": "5,297,402,353,460", "frmtrm_nm": "제 42 기", "frmtrm_dt": "2014.01.01 ~ 2014.12.31", "frmtrm_amount": "4,783,988,805,326", "bfefrmtrm_nm": "제 41 기", "bfefrmtrm_dt": "2013.01.01 ~ 2013.12.31", "bfefrmtrm_amount": "5,753,487,402,140", "ord": "24", "currency": "KRW"}, {"rcept_no": "20160330003977", "reprt_code": "11011", "bsns_year": "2015", "corp_code": "00126371", "stock_code": "009150", "fs_div": "OFS", "fs_nm": "재무제표", "sj_div": "IS", "sj_nm": "손익계산서", "account_nm": "영업이익", "thstrm_nm": "제 43 기", "thstrm_dt": "2015.01.01 ~ 2015.12.31", "thstrm_amount": "1,565,394,093", "frmtrm_nm": "제 42 기", "frmtrm_dt": "2014.01.01 ~ 2014.12.31", "frmtrm_amount": "-130,733,607,297", "bfefrmtrm_nm": "제 41 기", "bfefrmtrm_dt": "2013.01.01 ~ 2013.12.31", "bfefrmtrm_amount": "389,106,991,192", "ord": "26", "currency": "KRW"}, {"rcept_no": "20160330003977", "reprt_code": "11011", "bsns_year": "2015", "corp_code": "00126371", "stock_code": "009150", "fs_div": "OFS", "fs_nm": "재무제표", "sj_div": "IS", "sj_nm": "손익계산서", "account_nm": "법인세차감전 순이익", "thstrm_nm": "제 43 기", "thstrm_dt": "2015.01.01 ~ 2015.12.31", "thstrm_amount": "236,747,906,935", "frmtrm_nm": "제 42 기", "frmtrm_dt": "2014.01.01 ~ 2014.12.31", "frmtrm_amount": "646,798,155,417", "bfefrmtrm_nm": "제 41 기", "bfefrmtrm_dt": "2013.01.01 ~ 2013.12.31", "bfefrmtrm_amount": "376,168,968,813", "ord": "28", "currency": "KRW"}, {"rcept_no": "20160330003977", "reprt_code": "11011", "bsns_year": "2015", "corp_code": "00126371", "stock_code": "009150", "fs_div": "OFS", "fs_nm": "재무제표", "sj_div": "IS", "sj_nm": "손익계산서", "account_nm": "당기순이익(손실)", "thstrm_nm": "제 43 기", "thstrm_dt": "2015.01.01 ~ 2015.12.31", "thstrm_amount": "118,432,190,852", "frmtrm_nm": "제 42 기", "frmtrm_dt": "2014.01.01 ~ 2014.12.31", "frmtrm_amount": "451,590,148,965", "bfefrmtrm_nm": "제 41 기", "bfefrmtrm_dt": "2013.01.01 ~ 2013.12.31", "bfefrmtrm_amount": "244,228,739,260", "ord": "30", "currency": "KRW"}, {"rcept_no": "20160330003977", "reprt_code": "11011", "bsns_year": "2015", "corp_code": "00126371", "stock_code": "009150", "fs_div": "OFS", "fs_nm": "재무제표", "sj_div": "IS", "sj_nm": "손익계산서", "account_nm": "당기순이익(손실)", "thstrm_nm": "제 43 기", "thstrm_dt": "2015.01.01 ~ 2015.12.31", "thstrm_amount": "118,432,190,852", "frmtrm_nm": "제 42 기", "frmtrm_dt": "2014.01.01 ~ 2014.12.31", "frmtrm_amount": "451,590,148,965", "bfefrmtrm_nm": "제 41 기", "bfefrmtrm_dt": "2013.01.01 ~ 2013.12.31", "bfefrmtrm_amount": "244,228,739,260", "ord": "62", "currency": "KRW"}]}