{"status": "000", "message": "정상", "list": [{"rcept_no": "20220321001237", "reprt_code": "11011", "bsns_year": "2021", "corp_code": "00120021", "stock_code": "003550", "fs_div": "CFS", "fs_nm": "연결재무제표", "sj_div": "BS", "sj_nm": "재무상태표", "account_nm": "유동자산", "thstrm_nm": "제 60 기", "thstrm_dt": "2021.12.31 현재", "thstrm_amount": "5,547,934,000,000", "frmtrm_nm": "제 59 기", "frmtrm_dt": "2020.12.31 현재", "frmtrm_amount": "5,895,921,000,000", "bfefrmtrm_nm": "제 58 기", "bfefrmtrm_dt": "2019.12.31 현재", "bfefrmtrm_amount": "3,939,057,000,000", "ord": "1", "currency": "KRW"}, {"rcept_no": "20220321001237", "reprt_code": "11011", "bsns_year": "2021", "corp_code": "00120021", "stock_code": "003550", "fs_div": "CFS", "fs_nm": "연결재무제표", "sj_div": "BS", "sj_nm": "재무상태표", "account_nm": "비유동자산", "thstrm_nm": "제 60 기", "thstrm_dt": "2021.12.31 현재", "thstrm_amount": "20,121,862,000,000", "frmtrm_nm": "제 59 기", "frmtrm_dt": "2020.12.31 현재", "frmtrm_amount": "18,386,347,000,000", "bfefrmtrm_nm": "제 58 기", "bfefrmtrm_dt": "2019.12.31 현재", "bfefrmtrm_amount": "18,495,573,000,000", "ord": "3", "currency": "KRW"}, {"rcept_no": "20220321001237", "reprt_code": "11011", "bsns_year": "2021", "corp_code": "00120021", "stock_code": "003550", "fs_div": "CFS", "fs_nm": "연결재무제표", "sj_div": "BS", "sj_nm": "재무상태표", "account_nm": "자산총계", "thstrm_nm": "제 60 기", "thstrm_dt": "2021.12.31 현재", "thstrm_amount": "25,669,796,000,000", "frmtrm_nm": "제 59 기", "frmtrm_dt": "2020.12.31 현재", "frmtrm_amount": "24,282,268,000,000", "bfefrmtrm_nm": "제 58 기", "bfefrmtrm_dt": "2019.12.31 현재", "bfefrmtrm_amount": "22,434,630,000,000", "ord": "5", "currency": "KRW"}, {"rcept_no": "20220321001237", "reprt_code": "11011", "bsns_year": "2021", "corp_code": "00120021", "stock_code": "003550", "fs_div": "CFS", "fs_nm": "연결재무제표", "sj_div": "BS", "sj_nm": "재무상태표", "account_nm": "유동부채", "thstrm_nm": "제 60 기", "thstrm_dt": "2021.12.31 현재", "thstrm_amount": "2,819,273,000,000", "frmtrm_nm": "제 59 기", "frmtrm_dt": "2020.12.31 현재", "frmtrm_amount": "2,133,263,000,000", "bfefrmtrm_nm": "제 58 기", "bfefrmtrm_dt": "2019.12.31 현재", "bfefrmtrm_amount": "2,244,801,000,000", "ord": "7", "currency": "KRW"}, {"rcept_no": "20220321001237", "reprt_code": "11011", "bsns_year": "2021", "corp_code": "00120021", "stock_code": "003550", "fs_div": "CFS", "fs_nm": "연결재무제표", "sj_div": "BS", "sj_nm": "재무상태표", "account_nm": "비유동부채", "thstrm_nm": "제 60 기", "thstrm_dt": "2021.12.31 현재", "thstrm_amount": "910,302,000,000", "frmtrm_nm": "제 59 기", "frmtrm_dt": "2020.12.31 현재", "frmtrm_amount": "1,287,715,000,000", "bfefrmtrm_nm": "제 58 기", "bfefrmtrm_dt": "2019.12.31 현재", "bfefrmtrm_amount": "1,168,808,000,000", "ord": "9", "currency": "KRW"}, {"rcept_no": "20220321001237", "reprt_code": "11011", "bsns_year": "2021", "corp_code": "00120021", "stock_code": "003550", "fs_div": "CFS", "fs_nm": "연결재무제표", "sj_div": "BS", "sj_nm": "재무상태표", "account_nm": "부채총계", "thstrm_nm": "제 60 기", "thstrm_dt": "2021.12.31 현재", "thstrm_amount": "3,729,575,000,000", "frmtrm_nm": "제 59 기", "frmtrm_dt": "2020.12.31 현재", "frmtrm_amount": "3,420,978,000,000", "bfefrmtrm_nm": "제 58 기", "bfefrmtrm_dt": "2019.12.31 현재", "bfefrmtrm_amount": "3,413,609,000,000", "ord": "11", "currency": "KRW"}, {"rcept_no": "20220321001237", "reprt_code": "11011", "bsns_year": "2021", "corp_code": "00120021", "stock_code": "003550", "fs_div": "CFS", "fs_nm": "연결재무제표", "sj_div": "BS", "sj_nm": "재무상태표", "account_nm": "자본금", "thstrm_nm": "제 60 기", "thstrm_dt": "2021.12.31 현재", "thstrm_amount": "801,613,000,000", "frmtrm_nm": "제 59 기", "frmtrm_dt": "2020.12.31 현재", "frmtrm_amount": "879,359,000,000", "bfefrmtrm_nm": "제 58 기", "bfefrmtrm_dt": "2019.12.31 현재", "bfefrmtrm_amount": "879,359,000,000", "ord": "13", "currency": "KRW"}, {"rcept_no": "20220321001237", "reprt_code": "11011", "bsns_year": "2021", "corp_code": "00120021", "stock_code": "003550", "fs_div": "CFS", "fs_nm": "연결재무제표", "sj_div": "BS", "sj_nm": "재무상태표", "account_nm": "이익잉여금", "thstrm_nm": "제 60 기", "thstrm_dt": "2021.12.31 현재", "thstrm_amount": "18,891,414,000,000", "frmtrm_nm": "제 59 기", "frmtrm_dt": "2020.12.31 현재", "frmtrm_amount": "16,782,359,000,000", "bfefrmtrm_nm": "제 58 기", "bfefrmtrm_dt": "2019.12.31 현재", "bfefrmtrm_amount": "15,699,266,000,000", "ord": "17", "currency": "KRW"}, {"rcept_no": "20220321001237", "reprt_code": "11011", "bsns_year": "2021", "corp_code": "00120021", "stock_code": "003550", "fs_div": "CFS", "fs_nm": "연결재무제표", "sj_div": "BS", "sj_nm": "재무상태표", "account_nm": "자본총계", "thstrm_nm": "제 60 기", "thstrm_dt": "2021.12.31 현재", "thstrm_amount": "21,940,221,000,000", "frmtrm_nm": "제 59 기", "frmtrm_dt": "2020.12.31 현재", "frmtrm_amount": "20,861,290,000,000", "bfefrmtrm_nm": "제 58 기", "bfefrmtrm_dt": "2019.12.31 현재", "bfefrmtrm_amount": "19,021,021,000,000", "ord": "21", "currency": "KRW"}, {"rcept_no": "20220321001237", "reprt_code": "11011", "bsns_year": "2021", "corp_code": "00120021", "stock_code": "003550", "fs_div": "CFS", "fs_nm": "연결재무제표", "sj_div": "IS", "sj_nm": "손익계산서", "account_nm": "매출액", "thstrm_nm": "제 60 기", "thstrm_dt": "2021.01.01 ~ 2021.12.31", "thstrm_amount": "6,859,010,000,000", "frmtrm_nm": "제 59 기", "frmtrm_dt": "2020.01.01 ~ 2020.12.31", "frmtrm_amount": "5,199,070,000,000", "bfefrmtrm_nm": "제 58 기", "bfefrmtrm_dt": "2019.01.01 ~ 2019.12.31", "bfefrmtrm_amount": "4,427,534,000,000", "ord": "23", "currency": "KRW"}, {"rcept_no": "20220321001237", "reprt_code": "11011", "bsns_year": "2021", "corp_code": "00120021", "stock_code": "003550", "fs_div": "CFS", "fs_nm": "연결재무제표", "sj_div": "IS", "sj_nm": "손익계산서", "account_nm": "영업이익", "thstrm_nm": "제 60 기", "thstrm_dt": "2021.01.01 ~ 2021.12.31", "thstrm_amount": "2,460,104,000,000", "frmtrm_nm": "제 59 기", "frmtrm_dt": "2020.01.01 ~ 2020.12.31", "frmtrm_amount": "1,586,056,000,000", "bfefrmtrm_nm": "제 58 기", "bfefrmtrm_dt": "2019.01.01 ~ 2019.12.31", "bfefrmtrm_amount": "841,193,000,000", "ord": "25", "currency": "KRW"}, {"rcept_no": "20220321001237", "reprt_code": "11011", "bsns_year": "2021", "corp_code": "00120021", "stock_code": "003550", "fs_div": "CFS", "fs_nm": "연결재무제표", "sj_div": "IS", "sj_nm": "손익계산서", "account_nm": "법인세차감전 순이익", "thstrm_nm": "제 60 기", "thstrm_dt": "2021.01.01 ~ 2021.12.31", "thstrm_amount": "2,390,985,000,000", "frmtrm_nm": "제 59 기", "frmtrm_dt": "2020.01.01 ~ 2020.12.31", "frmtrm_amount": "1,643,100,000,000", "bfefrmtrm_nm": "제 58 기", "bfefrmtrm_dt": "2019.01.01 ~ 2019.12.31", "bfefrmtrm_amount": "830,944,000,000", "ord": "27", "currency": "KRW"}, {"rcept_no": "20220321001237", "reprt_code": "11011", "bsns_year": "2021", "corp_code": "00120021", "stock_code": "003550", "fs_div": "CFS", "fs_nm": "연결재무제표", "sj_div": "IS", "sj_nm": "손익계산서", "account_nm": "당기순이익(손실)", "thstrm_nm": "제 60 기", "thstrm_dt": "2021.01.01 ~ 2021.12.31", "thstrm_amount": "2,683,974,000,000", "frmtrm_nm": "제 59 기", "frmtrm_dt": "2020.01.01 ~ 2020.12.31", "frmtrm_amount": "1,540,658,000,000", "bfefrmtrm_nm": "제 58 기", "bfefrmtrm_dt": "2019.01.01 ~ 2019.12.31", "bfefrmtrm_amount": "1,106,755,000,000", "ord": "29", "currency": "KRW"}, {"rcept_no": "20220321001237", "reprt_code": "11011", "bsns_year": "2021", "corp_code": "00120021", "stock_code": "003550", "fs_div": "CFS", "fs_nm": "연결재무제표", "sj_div": "IS", "sj_nm": "손익계산서", "account_nm": "당기순이익(손실)", "thstrm_nm": "제 60 기", "thstrm_dt": "2021.01.01 ~ 2021.12.31", "thstrm_amount": "2,683,974,000,000", "frmtrm_nm": "제 59 기", "frmtrm_dt": "2020.01.01 ~ 2020.12.31", "frmtrm_amount": "1,540,658,000,000", "bfefrmtrm_nm": "제 58 기", "bfefrmtrm_dt": "2019.01.01 ~ 2019.12.31", "bfefrmtrm_amount": "1,106,755,000,000", "ord": "61", "currency": "KRW"}, {"rcept_no": "20220321001237", "reprt_code": "11011", "bsns_year": "2021", "corp_code": "00120021", "stock_code": "003550", "fs_div": "OFS", "fs_nm": "재무제표", "sj_div": "BS", "sj_nm": "재무상태표", "account_nm": "유동자산", "thstrm_nm": "제 60 기", "thstrm_dt": "2021.12.31 현재", "thstrm_amount": "1,831,399,000,000", "frmtrm_nm": "제 59 기", "frmtrm_dt": "2020.12.31 현재", "frmtrm_amount": "2,546,281,000,000", "bfefrmtrm_nm": "제 58 기", "bfefrmtrm_dt": "2019.12.31 현재", "bfefrmtrm_amount": "826,059,000,000", "ord": "2", "currency": "KRW"}, {"rcept_no": "20220321001237", "reprt_code": "11011", "bsns_year": "2021", "corp_code": "00120021", "stock_code": "003550", "fs_div": "OFS", "fs_nm": "재무제표", "sj_div": "BS", "sj_nm": "재무상태표", "account_nm": "비유동자산", "thstrm_nm": "제 60 기", "thstrm_dt": "2021.12.31 현재", "thstrm_amount": "7,877,300,000,000", "frmtrm_nm": "제 59 기", "frmtrm_dt": "2020.12.31 현재", "frmtrm_amount": "8,024,559,000,000", "bfefrmtrm_nm": "제 58 기", "bfefrmtrm_dt": "2019.12.31 현재", "bfefrmtrm_amount": "8,751,902,000,000", "ord": "4", "currency": "KRW"}, {"rcept_no": "20220321001237", "reprt_code": "11011", "bsns_year": "2021", "corp_code": "00120021", "stock_code": "003550", "fs_div": "OFS", "fs_nm": "재무제표", "sj_div": "BS", "sj_nm": "재무상태표", "account_nm": "자산총계", "thstrm_nm": "제 60 기", "thstrm_dt": "2021.12.31 현재", "thstrm_amount": "9,708,699,000,000", "frmtrm_nm": "제 59 기", "frmtrm_dt": "2020.12.31 현재", "frmtrm_amount": "10,570,840,000,000", "bfefrmtrm_nm": "제 58 기", "bfefrmtrm_dt": "2019.12.31 현재", "bfefrmtrm_amount": "9,577,961,000,000", "ord": "6", "currency": "KRW"}, {"rcept_no": "20220321001237", "reprt_code": "11011", "bsns_year": "2021", "corp_code": "00120021", "stock_code": "003550", "fs_div": "OFS", "fs_nm": "재무제표", "sj_div": "BS", "sj_nm": "재무상태표", "account_nm": "유동부채", "thstrm_nm": "제 60 기", "thstrm_dt": "2021.12.31 현재", "thstrm_amount": "179,868,000,000", "frmtrm_nm": "제 59 기", "frmtrm_dt": "2020.12.31 현재", "frmtrm_amount": "178,795,000,000", "bfefrmtrm_nm": "제 58 기", "bfefrmtrm_dt": "2019.12.31 현재", "bfefrmtrm_amount": "156,049,000,000", "ord": "8", "currency": "KRW"}, {"rcept_no": "20220321001237", "reprt_code": "11011", "bsns_year": "2021", "corp_code": "00120021", "stock_code": "003550", "fs_div": "OFS", "fs_nm": "재무제표", "sj_div": "BS", "sj_nm": "재무상태표", "account_nm": "비유동부채", "thstrm_nm": "제 60 기", "thstrm_dt": "2021.12.31 현재", "thstrm_amount": "118,574,000,000", "frmtrm_nm": "제 59 기", "frmtrm_dt": "2020.12.31 현재", "frmtrm_amount": "122,248,000,000", "bfefrmtrm_nm": "제 58 기", "bfefrmtrm_dt": "2019.12.31 현재", "bfefrmtrm_amount": "95,167,000,000", "ord": "10", "currency": "KRW"}, {"rcept_no": "20220321001237", "reprt_code": "11011", "bsns_year": "2021", "corp_code": "00120021", "stock_code": "003550", "fs_div": "OFS", "fs_nm": "재무제표", "sj_div": "BS", "sj_nm": "재무상태표", "account_nm": "부채총계", "thstrm_nm": "제 60 기", "thstrm_dt": "2021.12.31 현재", "thstrm_amount": "298,442,000,000", "frmtrm_nm": "제 59 기", "frmtrm_dt": "2020.12.31 현재", "frmtrm_amount": "301,043,000,000", "bfefrmtrm_nm": "제 58 기", "bfefrmtrm_dt": "2019.12.31 현재", "bfefrmtrm_amount": "251,216,000,000", "ord": "12", "currency": "KRW"}, {"rcept_no": "20220321001237", "reprt_code": "11011", "bsns_year": "2021", "corp_code": "00120021", "stock_code": "003550", "fs_div": "OFS", "fs_nm": "재무제표", "sj_div": "BS", "sj_nm": "재무상태표", "account_nm": "자본금", "thstrm_nm": "제 60 기", "thstrm_dt": "2021.12.31 현재", "thstrm_amount": "801,613,000,000", "frmtrm_nm": "제 59 기", "frmtrm_dt": "2020.12.31 현재", "frmtrm_amount": "879,359,000,000", "bfefrmtrm_nm": "제 58 기", "bfefrmtrm_dt": "2019.12.31 현재", "bfefrmtrm_amount": "879,359,000,000", "ord": "15", "currency": "KRW"}, {"rcept_no": "20220321001237", "reprt_code": "11011", "bsns_year": "2021", "corp_code": "00120021", "stock_code": "003550", "fs_div": "OFS", "fs_nm": "재무제표", "sj_div": "BS", "sj_nm": "재무상태표", "account_nm": "이익잉여금", "thstrm_nm": "제 60 기", "thstrm_dt": "2021.12.31 현재", "thstrm_amount": "7,740,618,000,000", "frmtrm_nm": "제 59 기", "frmtrm_dt": "2020.12.31 현재", "frmtrm_amount": "6,947,881,000,000", "bfefrmtrm_nm": "제 58 기", "bfefrmtrm_dt": "2019.12.31 현재", "bfefrmtrm_amount": "6,003,695,000,000", "ord": "19", "currency": "KRW"}, {"rcept_no": "20220321001237", "reprt_code": "11011", "bsns_year": "2021", "corp_code": "00120021", "stock_code": "003550", "fs_div": "OFS", "fs_nm": "재무제표", "sj_div": "BS", "sj_nm": "재무상태표", "account_nm": "자본총계", "thstrm_nm": "제 60 기", "thstrm_dt": "2021.12.31 현재", "thstrm_amount": "9,410,257,000,000", "frmtrm_nm": "제 59 기", "frmtrm_dt": "2020.12.31 현재", "frmtrm_amount": "10,269,797,000,000", "bfefrmtrm_nm": "제 58 기", "bfefrmtrm_dt": "2019.12.31 현재", "bfefrmtrm_amount": "9,326,745,000,000", "ord": "22", "currency": "KRW"}, {"rcept_no": "20220321001237", "reprt_code": "11011", "bsns_year": "2021", "corp_code": "00120021", "stock_code": "003550", "fs_div": "OFS", "fs_nm": "재무제표", "sj_div": "IS", "sj_nm": "손익계산서", "account_nm": "매출액", "thstrm_nm": "제 60 기", "thstrm_dt": "2021.01.01 ~ 2021.12.31", "thstrm_amount": "989,760,000,000", "frmtrm_nm": "제 59 기", "frmtrm_dt": "2020.01.01 ~ 2020.12.31", "frmtrm_amount": "1,016,202,000,000", "bfefrmtrm_nm": "제 58 기", "bfefrmtrm_dt": "2019.01.01 ~ 2019.12.31", "bfefrmtrm_amount": "785,255,000,000", "ord": "24", "currency": "KRW"}, {"rcept_no": "20220321001237", "reprt_code": "11011", "bsns_year": "2021", "corp_code": "00120021", "stock_code": "003550", "fs_div": "OFS", "fs_nm": "재무제표", "sj_div": "IS", "sj_nm": "손익계산서", "account_nm": "영업이익", "thstrm_nm": "제 60 기", "thstrm_dt": "2021.01.01 ~ 2021.12.31", "thstrm_amount": "740,373,000,000", "frmtrm_nm": "제 59 기", "frmtrm_dt": "2020.01.01 ~ 2020.12.31", "frmtrm_amount": "794,023,000,000", "bfefrmtrm_nm": "제 58 기", "bfefrmtrm_dt": "2019.01.01 ~ 2019.12.31", "bfefrmtrm_amount": "565,487,000,000", "ord": "26", "currency": "KRW"}, {"rcept_no": "20220321001237", "reprt_code": "11011", "bsns_year": "2021", "corp_code": "00120021", "stock_code": "003550", "fs_div": "OFS", "fs_nm": "재무제표", "sj_div": "IS", "sj_nm": "손익계산서", "account_nm": "법인세차감전 순이익", "thstrm_nm": "제 60 기", "thstrm_dt": "2021.01.01 ~ 2021.12.31", "thstrm_amount": "552,316,000,000", "frmtrm_nm": "제 59 기", "frmtrm_dt": "2020.01.01 ~ 2020.12.31", "frmtrm_amount": "1,591,459,000,000", "bfefrmtrm_nm": "제 58 기", "bfefrmtrm_dt": "2019.01.01 ~ 2019.12.31", "bfefrmtrm_amount": "578,308,000,000", "ord": "28", "currency": "KRW"}, {"rcept_no": "20220321001237", "reprt_code": "11011", "bsns_year": "2021", "corp_code": "00120021", "stock_code": "003550", "fs_div": "OFS", "fs_nm": "재무제표", "sj_div": "IS", "sj_nm": "손익계산서", "account_nm": "당기순이익(손실)", "thstrm_nm": "제 60 기", "thstrm_dt": "2021.01.01 ~ 2021.12.31", "thstrm_amount": "1,234,012,000,000", "frmtrm_nm": "제 59 기", "frmtrm_dt": "2020.01.01 ~ 2020.12.31", "frmtrm_amount": "1,331,351,000,000", "bfefrmtrm_nm": "제 58 기", "bfefrmtrm_dt": "2019.01.01 ~ 2019.12.31", "bfefrmtrm_amount": "581,161,000,000", "ord": "30", "currency": "KRW"}, {"rcept_no": "20220321001237", "reprt_code": "11011", "bsns_year": "2021", "corp_code": "00120021", "stock_code": "003550", "fs_div": "OFS", "fs_nm": "재무제표", "sj_div": "IS", "sj_nm": "손익계산서", "account_nm": "당기순이익(손실)", "thstrm_nm": "제 60 기", "thstrm_dt": "2021.01.01 ~ 2021.12.31", "thstrm_amount": "1,234,012,000,000", "frmtrm_nm": "제 59 기", "frmtrm_dt": "2020.01.01 ~ 2020.12.31", "frmtrm_amount": "1,331,351,000,000", "bfefrmtrm_nm": "제 58 기", "bfefrmtrm_dt": "2019.01.01 ~ 2019.12.31", "bfefrmtrm_amount": "581,161,000,000", "ord": "62", "currency": "KRW"}]}