{"status": "000", "message": "정상", "list": [{"rcept_no": "20180330002462", "reprt_code": "11011", "bsns_year": "2017", "corp_code": "00258801", "stock_code": "035720", "fs_div": "CFS", "fs_nm": "연결재무제표", "sj_div": "BS", "sj_nm": "재무상태표", "account_nm": "유동자산", "thstrm_nm": "제 23 기", "thstrm_dt": "2017.12.31 현재", "thstrm_amount": "1,993,096,161,071", "frmtrm_nm": "제 22 기", "frmtrm_dt": "2016.12.31 현재", "frmtrm_amount": "1,216,958,016,369", "bfefrmtrm_nm": "제 21 기", "bfefrmtrm_dt": "2015.12.31 현재", "bfefrmtrm_amount": "970,066,623,885", "ord": "1", "currency": "KRW"}, {"rcept_no": "20180330002462", "reprt_code": "11011", "bsns_year": "2017", "corp_code": "00258801", "stock_code": "035720", "fs_div": "CFS", "fs_nm": "연결재무제표", "sj_div": "BS", "sj_nm": "재무상태표", "account_nm": "비유동자산", "thstrm_nm": "제 23 기", "thstrm_dt": "2017.12.31 현재", "thstrm_amount": "4,356,332,293,816", "frmtrm_nm": "제 22 기", "frmtrm_dt": "2016.12.31 현재", "frmtrm_amount": "4,267,159,164,047", "bfefrmtrm_nm": "제 21 기", "bfefrmtrm_dt": "2015.12.31 현재", "bfefrmtrm_amount": "2,218,411,109,424", "ord": "3", "currency": "KRW"}, {"rcept_no": "20180330002462", "reprt_code": "11011", "bsns_year": "2017", "corp_code": "00258801", "stock_code": "035720", "fs_div": "CFS", "fs_nm": "연결재무제표", "sj_div": "BS", "sj_nm": "재무상태표", "account_nm": "자산총계", "thstrm_nm": "제 23 기", "thstrm_dt": "2017.12.31 현재", "thstrm_amount": "6,349,428,454,887", "frmtrm_nm": "제 22 기", "frmtrm_dt": "2016.12.31 현재", "frmtrm_amount": "5,484,117,180,416", "bfefrmtrm_nm": "제 21 기", "bfefrmtrm_dt": "2015.12.31 현재", "bfefrmtrm_amount": "3,188,477,733,309", "ord": "5", "currency": "KRW"}, {"rcept_no": "20180330002462", "reprt_code": "11011", "bsns_year": "2017", "corp_code": "00258801", "stock_code": "035720", "fs_div": "CFS", "fs_nm": "연결재무제표", "sj_div": "BS", "sj_nm": "재무상태표", "account_nm": "유동부채", "thstrm_nm": "제 23 기", "thstrm_dt": "2017.12.31 현재", "thstrm_amount": "1,040,863,175,362", "frmtrm_nm": "제 22 기", "frmtrm_dt": "2016.12.31 현재", "frmtrm_amount": "806,019,918,989", "bfefrmtrm_nm": "제 21 기", "bfefrmtrm_dt": "2015.12.31 현재", "bfefrmtrm_amount": "316,078,102,307", "ord": "7", "currency": "KRW"}, {"rcept_no": "20180330002462", "reprt_code": "11011", "bsns_year": "2017", "corp_code": "00258801", "stock_code": "035720", "fs_div": "CFS", "fs_nm": "연결재무제표", "sj_div": "BS", "sj_nm": "재무상태표", "account_nm": "비유동부채", "thstrm_nm": "제 23 기", "thstrm_dt": "2017.12.31 현재", "thstrm_amount": "800,745,474,158", "frmtrm_nm": "제 22 기", "frmtrm_dt": "2016.12.31 현재", "frmtrm_amount": "975,153,410,479", "bfefrmtrm_nm": "제 21 기", "bfefrmtrm_dt": "2015.12.31 현재", "bfefrmtrm_amount": "286,924,635,375", "ord": "9", "currency": "KRW"}, {"rcept_no": "20180330002462", "reprt_code": "11011", "bsns_year": "2017", "corp_code": "00258801", "stock_code": "035720", "fs_div": "CFS", "fs_nm": "연결재무제표", "sj_div": "BS", "sj_nm": "재무상태표", "account_nm": "부채총계", "thstrm_nm": "제 23 기", "thstrm_dt": "2017.12.31 현재", "thstrm_amount": "1,841,608,649,520", "frmtrm_nm": "제 22 기", "frmtrm_dt": "2016.12.31 현재", "frmtrm_amount": "1,781,173,329,468", "bfefrmtrm_nm": "제 21 기", "bfefrmtrm_dt": "2015.12.31 현재", "bfefrmtrm_amount": "603,002,737,682", "ord": "11", "currency": "KRW"}, {"rcept_no": "20180330002462", "reprt_code": "11011", "bsns_year": "2017", "corp_code": "00258801", "stock_code": "035720", "fs_div": "CFS", "fs_nm": "연결재무제표", "sj_div": "BS", "sj_nm": "재무상태표", "account_nm": "자본금", "thstrm_nm": "제 23 기", "thstrm_dt": "2017.12.31 현재", "thstrm_amount": "34,004,263,500", "frmtrm_nm": "제 22 기", "frmtrm_dt": "2016.12.31 현재", "frmtrm_amount": "33,857,857,500", "bfefrmtrm_nm": "제 21 기", "bfefrmtrm_dt": "2015.12.31 현재", "bfefrmtrm_amount": "30,098,044,000", "ord": "13", "currency": "KRW"}, {"rcept_no": "20180330002462", "reprt_code": "11011", "bsns_year": "2017", "corp_code": "00258801", "stock_code": "035720", "fs_div": "CFS", "fs_nm": "연결재무제표", "sj_div": "BS", "sj_nm": "재무상태표", "account_nm": "이익잉여금", "thstrm_nm": "제 23 기", "thstrm_dt": "2017.12.31 현재", "thstrm_amount": "402,542,351,524", "frmtrm_nm": "제 22 기", "frmtrm_dt": "2016.12.31 현재", "frmtrm_amount": "303,952,022,714", "bfefrmtrm_nm": "제 21 기", "bfefrmtrm_dt": "2015.12.31 현재", "bfefrmtrm_amount": "256,313,358,089", "ord": "17", "currency": "KRW"}, {"rcept_no": "20180330002462", "reprt_code": "11011", "bsns_year": "2017", "corp_code": "00258801", "stock_code": "035720", "fs_div": "CFS", "fs_nm": "연결재무제표", "sj_div": "BS", "sj_nm": "재무상태표", "account_nm": "자본총계", "thstrm_nm": "제 23 기", "thstrm_dt": "2017.12.31 현재", "thstrm_amount": "4,507,819,805,367", "frmtrm_nm": "제 22 기", "frmtrm_dt": "2016.12.31 현재", "frmtrm_amount": "3,702,943,850,948", "bfefrmtrm_nm": "제 21 기", "bfefrmtrm_dt": "2015.12.31 현재", "bfefrmtrm_amount": "2,585,474,995,627", "ord": "21", "currency": "KRW"}, {"rcept_no": "20180330002462", "reprt_code": "11011", "bsns_year": "2017", "corp_code": "00258801", "stock_code": "035720", "fs_div": "CFS", "fs_nm": "연결재무제표", "sj_div": "IS", "sj_nm": "손익계산서", "account_nm": "영업이익", "thstrm_nm": "제 23 기", "thstrm_dt": "2017.01.01 ~ 2017.12.31", "thstrm_amount": "165,379,527,605", "frmtrm_nm": "제 22 기", "frmtrm_dt": "2016.01.01 ~ 2016.12.31", "frmtrm_amount": "116,135,055,801", "bfefrmtrm_nm": "제 21 기", "bfefrmtrm_dt": "2015.01.01 ~ 2015.12.31", "bfefrmtrm_amount": "88,588,297,005", "ord": "25", "currency": "KRW"}, {"rcept_no": "20180330002462", "reprt_code": "11011", "bsns_year": "2017", "corp_code": "00258801", "stock_code": "035720", "fs_div": "CFS", "fs_nm": "연결재무제표", "sj_div": "IS", "sj_nm": "손익계산서", "account_nm": "법인세차감전 순이익", "thstrm_nm": "제 23 기", "thstrm_dt": "2017.01.01 ~ 2017.12.31", "thstrm_amount": "153,297,725,400", "frmtrm_nm": "제 22 기", "frmtrm_dt": "2016.01.01 ~ 2016.12.31", "frmtrm_amount": "100,295,612,108", "bfefrmtrm_nm": "제 21 기", "bfefrmtrm_dt": "2015.01.01 ~ 2015.12.31", "bfefrmtrm_amount": "109,542,968,750", "ord": "27", "currency": "KRW"}, {"rcept_no": "20180330002462", "reprt_code": "11011", "bsns_year": "2017", "corp_code": "00258801", "stock_code": "035720", "fs_div": "CFS", "fs_nm": "연결재무제표", "sj_div": "IS", "sj_nm": "손익계산서", "account_nm": "당기순이익(손실)", "thstrm_nm": "제 23 기", "thstrm_dt": "2017.01.01 ~ 2017.12.31", "thstrm_amount": "125,093,899,312", "frmtrm_nm": "제 22 기", "frmtrm_dt": "2016.01.01 ~ 2016.12.31", "frmtrm_amount": "65,455,116,983", "bfefrmtrm_nm": "제 21 기", "bfefrmtrm_dt": "2015.01.01 ~ 2015.12.31", "bfefrmtrm_amount": "78,764,757,714", "ord": "29", "currency": "KRW"}, {"rcept_no": "20180330002462", "reprt_code": "11011", "bsns_year": "2017", "corp_code": "00258801", "stock_code": "035720", "fs_div": "CFS", "fs_nm": "연결재무제표", "sj_div": "IS", "sj_nm": "손익계산서", "account_nm": "당기순이익(손실)", "thstrm_nm": "제 23 기", "thstrm_dt": "2017.01.01 ~ 2017.12.31", "thstrm_amount": "125,093,899,312", "frmtrm_nm": "제 22 기", "frmtrm_dt": "2016.01.01 ~ 2016.12.31", "frmtrm_amount": "65,455,116,983", "bfefrmtrm_nm": "제 21 기", "bfefrmtrm_dt": "2015.01.01 ~ 2015.12.31", "bfefrmtrm_amount": "78,764,757,714", "ord": "61", "currency": "KRW"}, {"rcept_no": "20180330002462", "reprt_code": "11011", "bsns_year": "2017", "corp_code": "00258801", "stock_code": "035720", "fs_div": "OFS", "fs_nm": "재무제표", "sj_div": "BS", "sj_nm": "재무상태표", "account_nm": "유동자산", "thstrm_nm": "제 23 기", "thstrm_dt": "2017.12.31 현재", "thstrm_amount": "632,508,485,022", "frmtrm_nm": "제 22 기", "frmtrm_dt": "2016.12.31 현재", "frmtrm_amount": "511,066,507,579", "bfefrmtrm_nm": "제 21 기", "bfefrmtrm_dt": "2015.12.31 현재", "bfefrmtrm_amount": "718,533,480,124", "ord": "2", "currency": "KRW"}, {"rcept_no": "20180330002462", "reprt_code": "11011", "bsns_year": "2017", "corp_code": "00258801", "stock_code": "035720", "fs_div": "OFS", "fs_nm": "재무제표", "sj_div": "BS", "sj_nm": "재무상태표", "account_nm": "비유동자산", "thstrm_nm": "제 23 기", "thstrm_dt": "2017.12.31 현재", "thstrm_amount": "4,324,369,371,075", "frmtrm_nm": "제 22 기", "frmtrm_dt": "2016.12.31 현재", "frmtrm_amount": "4,318,230,482,255", "bfefrmtrm_nm": "제 21 기", "bfefrmtrm_dt": "2015.12.31 현재", "bfefrmtrm_amount": "2,398,530,549,067", "ord": "4", "currency": "KRW"}, {"rcept_no": "20180330002462", "reprt_code": "11011", "bsns_year": "2017", "corp_code": "00258801", "stock_code": "035720", "fs_div": "OFS", "fs_nm": "재무제표", "sj_div": "BS", "sj_nm": "재무상태표", "account_nm": "자산총계", "thstrm_nm": "제 23 기", "thstrm_dt": "2017.12.31 현재", "thstrm_amount": "4,956,877,856,097", "frmtrm_nm": "제 22 기", "frmtrm_dt": "2016.12.31 현재", "frmtrm_amount": "4,829,296,989,834", "bfefrmtrm_nm": "제 21 기", "bfefrmtrm_dt": "2015.12.31 현재", "bfefrmtrm_amount": "3,117,064,029,191", "ord": "6", "currency": "KRW"}, {"rcept_no": "20180330002462", "reprt_code": "11011", "bsns_year": "2017", "corp_code": "00258801", "stock_code": "035720", "fs_div": "OFS", "fs_nm": "재무제표", "sj_div": "BS", "sj_nm": "재무상태표", "account_nm": "유동부채", "thstrm_nm": "제 23 기", "thstrm_dt": "2017.12.31 현재", "thstrm_amount": "948,930,789,986", "frmtrm_nm": "제 22 기", "frmtrm_dt": "2016.12.31 현재", "frmtrm_amount": "813,859,221,471", "bfefrmtrm_nm": "제 21 기", "bfefrmtrm_dt": "2015.12.31 현재", "bfefrmtrm_amount": "265,747,121,960", "ord": "8", "currency": "KRW"}, {"rcept_no": "20180330002462", "reprt_code": "11011", "bsns_year": "2017", "corp_code": "00258801", "stock_code": "035720", "fs_div": "OFS", "fs_nm": "재무제표", "sj_div": "BS", "sj_nm": "재무상태표", "account_nm": "비유동부채", "thstrm_nm": "제 23 기", "thstrm_dt": "2017.12.31 현재", "thstrm_amount": "450,237,479,800", "frmtrm_nm": "제 22 기", "frmtrm_dt": "2016.12.31 현재", "frmtrm_amount": "640,279,859,992", "bfefrmtrm_nm": "제 21 기", "bfefrmtrm_dt": "2015.12.31 현재", "bfefrmtrm_amount": "276,435,242,355", "ord": "10", "currency": "KRW"}, {"rcept_no": "20180330002462", "reprt_code": "11011", "bsns_year": "2017", "corp_code": "00258801", "stock_code": "035720", "fs_div": "OFS", "fs_nm": "재무제표", "sj_div": "BS", "sj_nm": "재무상태표", "account_nm": "부채총계", "thstrm_nm": "제 23 기", "thstrm_dt": "2017.12.31 현재", "thstrm_amount": "1,399,168,269,786", "frmtrm_nm": "제 22 기", "frmtrm_dt": "2016.12.31 현재", "frmtrm_amount": "1,454,139,081,463", "bfefrmtrm_nm": "제 21 기", "bfefrmtrm_dt": "2015.12.31 현재", "bfefrmtrm_amount": "542,182,364,315", "ord": "12", "currency": "KRW"}, {"rcept_no": "20180330002462", "reprt_code": "11011", "bsns_year": "2017", "corp_code": "00258801", "stock_code": "035720", "fs_div": "OFS", "fs_nm": "재무제표", "sj_div": "BS", "sj_nm": "재무상태표", "account_nm": "자본금", "thstrm_nm": "제 23 기", "thstrm_dt": "2017.12.31 현재", "thstrm_amount": "34,004,263,500", "frmtrm_nm": "제 22 기", "frmtrm_dt": "2016.12.31 현재", "frmtrm_amount": "33,857,857,500", "bfefrmtrm_nm": "제 21 기", "bfefrmtrm_dt": "2015.12.31 현재", "bfefrmtrm_amount": "30,098,044,000", "ord": "15", "currency": "KRW"}, {"rcept_no": "20180330002462", "reprt_code": "11011", "bsns_year": "2017", "corp_code": "00258801", "stock_code": "035720", "fs_div": "OFS", "fs_nm": "재무제표", "sj_div": "BS", "sj_nm": "재무상태표", "account_nm": "이익잉여금", "thstrm_nm": "제 23 기", "thstrm_dt": "2017.12.31 현재", "thstrm_amount": "497,769,298,138", "frmtrm_nm": "제 22 기", "frmtrm_dt": "2016.12.31 현재", "frmtrm_amount": "290,221,821,390", "bfefrmtrm_nm": "제 21 기", "bfefrmtrm_dt": "2015.12.31 현재", "bfefrmtrm_amount": "262,085,544,550", "ord": "19", "currency": "KRW"}, {"rcept_no": "20180330002462", "reprt_code": "11011", "bsns_year": "2017", "corp_code": "00258801", "stock_code": "035720", "fs_div": "OFS", "fs_nm": "재무제표", "sj_div": "BS", "sj_nm": "재무상태표", "account_nm": "자본총계", "thstrm_nm": "제 23 기", "thstrm_dt": "2017.12.31 현재", "thstrm_amount": "3,557,709,586,311", "frmtrm_nm": "제 22 기", "frmtrm_dt": "2016.12.31 현재", "frmtrm_amount": "3,375,157,908,371", "bfefrmtrm_nm": "제 21 기", "bfefrmtrm_dt": "2015.12.31 현재", "bfefrmtrm_amount": "2,574,881,664,876", "ord": "22", "currency": "KRW"}, {"rcept_no": "20180330002462", "reprt_code": "11011", "bsns_year": "2017", "corp_code": "00258801", "stock_code": "035720", "fs_div": "OFS", "fs_nm": "재무제표", "sj_div": "IS", "sj_nm": "손익계산서", "account_nm": "영업이익", "thstrm_nm": "제 23 기", "thstrm_dt": "2017.01.01 ~ 2017.12.31", "thstrm_amount": "97,550,822,849", "frmtrm_nm": "제 22 기", "frmtrm_dt": "2016.01.01 ~ 2016.12.31", "frmtrm_amount": "70,994,504,761", "bfefrmtrm_nm": "제 21 기", "bfefrmtrm_dt": "2015.01.01 ~ 2015.12.31", "bfefrmtrm_amount": "120,590,601,375", "ord": "26", "currency": "KRW"}, {"rcept_no": "20180330002462", "reprt_code": "11011", "bsns_year": "2017", "corp_code": "00258801", "stock_code": "035720", "fs_div": "OFS", "fs_nm": "재무제표", "sj_div": "IS", "sj_nm": "손익계산서", "account_nm": "법인세차감전 순이익", "thstrm_nm": "제 23 기", "thstrm_dt": "2017.01.01 ~ 2017.12.31", "thstrm_amount": "247,425,874,632", "frmtrm_nm": "제 22 기", "frmtrm_dt": "2016.01.01 ~ 2016.12.31", "frmtrm_amount": "52,624,706,327", "bfefrmtrm_nm": "제 21 기", "bfefrmtrm_dt": "2015.01.01 ~ 2015.12.31", "bfefrmtrm_amount": "101,204,258,334", "ord": "28", "currency": "KRW"}, {"rcept_no": "20180330002462", "reprt_code": "11011", "bsns_year": "2017", "corp_code": "00258801", "stock_code": "035720", "fs_div": "OFS", "fs_nm": "재무제표", "sj_div": "IS", "sj_nm": "손익계산서", "account_nm": "당기순이익(손실)", "thstrm_nm": "제 23 기", "thstrm_dt": "2017.01.01 ~ 2017.12.31", "thstrm_amount": "217,553,834,744", "frmtrm_nm": "제 22 기", "frmtrm_dt": "2016.01.01 ~ 2016.12.31", "frmtrm_amount": "38,171,457,140", "bfefrmtrm_nm": "제 21 기", "bfefrmtrm_dt": "2015.01.01 ~ 2015.12.31", "bfefrmtrm_amount": "72,897,764,237", "ord": "30", "currency": "KRW"}, {"rcept_no": "20180330002462", "reprt_code": "11011", "bsns_year": "2017", "corp_code": "00258801", "stock_code": "035720", "fs_div": "OFS", "fs_nm": "재무제표", "sj_div": "IS", "sj_nm": "손익계산서", "account_nm": "당기순이익(손실)", "thstrm_nm": "제 23 기", "thstrm_dt": "2017.01.01 ~ 2017.12.31", "thstrm_amount": "217,553,834,744", "frmtrm_nm": "제 22 기", "frmtrm_dt": "2016.01.01 ~ 2016.12.31", "frmtrm_amount": "38,171,457,140", "bfefrmtrm_nm": "제 21 기", "bfefrmtrm_dt": "2015.01.01 ~ 2015.12.31", "bfefrmtrm_amount": "72,897,764,237", "ord": "62", "currency": "KRW"}]}